{"assets":{"D6FDA76377A4B72BD709A19D5AB53409":{"type":"texture","index":7,"url":{"native":"assets\/B6D0338B-CDEE-454F-9DA9-FE75F497B692.pdf"},"width":177,"height":39},"0418E1174A020D26EEBE5FA4772E2C44":{"type":"texture","index":8,"url":{"native":"assets\/B6D0338B-CDEE-454F-9DA9-FE75F497B692.pdf"},"width":648,"height":50},"764AC2DAD017313B8416EA5D04A04BF8":{"type":"texture","index":6,"url":{"native":"assets\/B6D0338B-CDEE-454F-9DA9-FE75F497B692.pdf"},"width":464,"height":50},"CC1D75045AACEAD3DAAE3D3B7654F275":{"type":"texture","index":1,"url":{"native":"assets\/B6D0338B-CDEE-454F-9DA9-FE75F497B692.pdf"},"width":1803,"height":6},"B79D2036AB1E194906B9078B775C0A80":{"type":"texture","index":9,"url":{"native":"assets\/B6D0338B-CDEE-454F-9DA9-FE75F497B692.pdf"},"width":1920,"height":1080},"EA314A6407CB6C945B4C0DB198AACAF2":{"type":"texture","index":3,"url":{"native":"assets\/B6D0338B-CDEE-454F-9DA9-FE75F497B692.pdf"},"width":181,"height":56},"B91F7CE3C9C210F11E0B0C8265F67F38":{"type":"texture","index":5,"url":{"native":"assets\/B6D0338B-CDEE-454F-9DA9-FE75F497B692.pdf"},"width":521,"height":51},"6DA4FD3155B1C94EE0AADF8C1DE99484":{"type":"texture","index":10,"url":{"native":"assets\/B6D0338B-CDEE-454F-9DA9-FE75F497B692.pdf"},"width":1920,"height":1080},"EFF14D30B06EA00E9E52AFFF50E90B03":{"type":"texture","index":2,"url":{"native":"assets\/B6D0338B-CDEE-454F-9DA9-FE75F497B692.pdf"},"width":332,"height":29},"338FB3DAC9706D521D9A50392316EF03":{"type":"texture","index":4,"url":{"native":"assets\/B6D0338B-CDEE-454F-9DA9-FE75F497B692.pdf"},"width":310,"height":41},"F060ECB2D3B13BDD8C493DD73E965B5C":{"type":"texture","index":0,"url":{"native":"assets\/B6D0338B-CDEE-454F-9DA9-FE75F497B692.pdf"},"width":1920,"height":1080}},"events":[{"effects":[{"beginTime":0,"baseLayer":{"animations":[],"initialState":{"affineTransform":[1,0,0,1,0,0],"masksToBounds":false,"rotation":0,"scale":1,"position":{"pointX":384,"pointY":539},"width":648,"sublayerTransform":[1,0,0,0,0,1,0,0,0,0,1,0,0,0,0,1],"contentsRect":{"y":0,"x":0,"width":1,"height":1},"opacity":1,"edgeAntialiasingMask":251658240,"height":470,"hidden":false,"anchorPoint":{"pointX":0.5,"pointY":0.5}},"objectID":"F3110F88-620E-4F0C-9883-9801311D1424","layers":[{"animations":[],"initialState":{"affineTransform":[1,0,0,1,0,0],"masksToBounds":false,"rotation":0,"scale":1,"position":{"pointX":900,"pointY":236},"width":648,"sublayerTransform":[1,0,0,0,0,1,0,0,0,0,1,-0.00035007912466775983,0,0,0,1],"contentsRect":{"y":0,"x":0,"width":1,"height":1},"opacity":1,"edgeAntialiasingMask":251658240,"height":470,"hidden":false,"anchorPoint":{"pointX":1.3888888888888888,"pointY":0.50212765957446803}},"layers":[{"animations":[{"additive":false,"timeOffset":0,"beginTime":1e-100,"repeatCount":0,"fillMode":"both","duration":0.001,"autoreverses":false,"animations":[{"additive":false,"timeOffset":0,"beginTime":0,"from":{"scalar":true},"repeatCount":0,"fillMode":"both","duration":0.0001,"autoreverses":false,"property":"hidden","to":{"scalar":false},"removedOnCompletion":true},{"additive":false,"timeOffset":0,"beginTime":0.0001,"from":{"scalar":false},"repeatCount":0,"fillMode":"forwards","duration":0.00089999999999999998,"autoreverses":false,"property":"hidden","to":{"scalar":false},"removedOnCompletion":true}],"removedOnCompletion":false}],"layers":[],"texturedRectangle":{"singleTextureOpacity":1,"textXHeight":0.55492682926829262,"textBaseline":0.9129787538109756,"isBackgroundTexture":false,"isVerticalText":false,"textColor":[0.83576232194900513,0.83576232194900513,0.83576232194900513,1],"textureType":6},"initialState":{"affineTransform":[1,0,0,1,0,0],"masksToBounds":false,"rotation":0,"scale":1,"position":{"pointX":167,"pointY":35.5},"width":310,"sublayerTransform":[1,0,0,0,0,1,0,0,0,0,1,0,0,0,0,1],"contentsRect":{"y":0,"x":0,"width":1,"height":1},"opacity":1,"edgeAntialiasingMask":0,"height":41,"hidden":true,"anchorPoint":{"pointX":0.5,"pointY":0.5}},"texture":"338FB3DAC9706D521D9A50392316EF03"}]},{"animations":[],"layers":[],"texturedRectangle":{"singleTextureOpacity":1,"textXHeight":0.44611764705882351,"textBaseline":0.75357115502450978,"isBackgroundTexture":false,"isVerticalText":false,"textColor":[0.83576232194900513,0.83576232194900513,0.83576232194900513,1],"textureType":6},"initialState":{"affineTransform":[1,0,0,1,0,0],"masksToBounds":false,"rotation":0,"scale":1,"position":{"pointX":272.5,"pointY":144.5},"width":521,"sublayerTransform":[1,0,0,0,0,1,0,0,0,0,1,0,0,0,0,1],"contentsRect":{"y":0,"x":0,"width":1,"height":1},"opacity":1,"edgeAntialiasingMask":0,"height":51,"hidden":true,"anchorPoint":{"pointX":0.5,"pointY":0.5}},"texture":"B91F7CE3C9C210F11E0B0C8265F67F38"},{"animations":[],"layers":[],"texturedRectangle":{"singleTextureOpacity":1,"textXHeight":0.45504,"textBaseline":0.74864257812500001,"isBackgroundTexture":false,"isVerticalText":false,"textColor":[0.83576232194900513,0.83576232194900513,0.83576232194900513,1],"textureType":6},"initialState":{"affineTransform":[1,0,0,1,0,0],"masksToBounds":false,"rotation":0,"scale":1,"position":{"pointX":244,"pointY":250},"width":464,"sublayerTransform":[1,0,0,0,0,1,0,0,0,0,1,0,0,0,0,1],"contentsRect":{"y":0,"x":0,"width":1,"height":1},"opacity":1,"edgeAntialiasingMask":0,"height":50,"hidden":true,"anchorPoint":{"pointX":0.5,"pointY":0.5}},"texture":"764AC2DAD017313B8416EA5D04A04BF8"},{"animations":[],"layers":[],"texturedRectangle":{"singleTextureOpacity":1,"textXHeight":0.58338461538461539,"textBaseline":0.90851612580128205,"isBackgroundTexture":false,"isVerticalText":false,"textColor":[0.83576232194900513,0.83576232194900513,0.83576232194900513,1],"textureType":6},"initialState":{"affineTransform":[1,0,0,1,0,0],"masksToBounds":false,"rotation":0,"scale":1,"position":{"pointX":100.5,"pointY":351.5},"width":177,"sublayerTransform":[1,0,0,0,0,1,0,0,0,0,1,0,0,0,0,1],"contentsRect":{"y":0,"x":0,"width":1,"height":1},"opacity":1,"edgeAntialiasingMask":0,"height":39,"hidden":true,"anchorPoint":{"pointX":0.5,"pointY":0.5}},"texture":"D6FDA76377A4B72BD709A19D5AB53409"},{"animations":[],"layers":[],"texturedRectangle":{"singleTextureOpacity":1,"textXHeight":0.45504,"textBaseline":0.74864257812500001,"isBackgroundTexture":false,"isVerticalText":false,"textColor":[0.83576232194900513,0.83576232194900513,0.83576232194900513,1],"textureType":6},"initialState":{"affineTransform":[1,0,0,1,0,0],"masksToBounds":false,"rotation":0,"scale":1,"position":{"pointX":336,"pointY":460},"width":648,"sublayerTransform":[1,0,0,0,0,1,0,0,0,0,1,0,0,0,0,1],"contentsRect":{"y":0,"x":0,"width":1,"height":1},"opacity":1,"edgeAntialiasingMask":0,"height":50,"hidden":true,"anchorPoint":{"pointX":0.5,"pointY":0.5}},"texture":"0418E1174A020D26EEBE5FA4772E2C44"}]},"effects":[],"duration":0.001,"type":"buildIn","attributes":{"direction":0},"name":"apple:bc-appear","objectID":"F3110F88-620E-4F0C-9883-9801311D1424"}],"automaticPlay":false,"hyperlinks":[],"accessibility":[{"text":"JoyFUL LOcal dev","targetRectangle":{"y":54,"x":64,"width":330.98554730415344,"height":42}},{"text":"Agenda","targetRectangle":{"y":174,"x":64,"width":178.21427999999997,"height":71.558220367431659}}],"baseLayer":{"animations":[],"initialState":{"affineTransform":[1,0,0,1,0,0],"masksToBounds":false,"rotation":0,"scale":1,"position":{"pointX":960,"pointY":540},"width":1920,"sublayerTransform":[1,0,0,0,0,1,0,0,0,0,1,0,0,0,0,1],"contentsRect":{"y":0,"x":0,"width":1,"height":1},"opacity":1,"edgeAntialiasingMask":251658240,"height":1080,"hidden":false,"anchorPoint":{"pointX":0.5,"pointY":0.5}},"layers":[{"animations":[],"initialState":{"affineTransform":[1,0,0,1,0,0],"masksToBounds":false,"rotation":0,"scale":1,"position":{"pointX":960,"pointY":540},"width":1920,"sublayerTransform":[1,0,0,0,0,1,0,0,0,0,1,0,0,0,0,1],"contentsRect":{"y":0,"x":0,"width":1,"height":1},"opacity":1,"edgeAntialiasingMask":251658240,"height":1080,"hidden":false,"anchorPoint":{"pointX":0.5,"pointY":0.5}},"layers":[{"animations":[],"initialState":{"affineTransform":[1,0,0,1,0,0],"masksToBounds":false,"rotation":0,"scale":1,"position":{"pointX":960,"pointY":540},"width":1920,"sublayerTransform":[1,0,0,0,0,1,0,0,0,0,1,0,0,0,0,1],"contentsRect":{"y":0,"x":0,"width":1,"height":1},"opacity":1,"edgeAntialiasingMask":251658240,"height":1080,"hidden":false,"anchorPoint":{"pointX":0.5,"pointY":0.5}},"layers":[{"animations":[],"layers":[],"texturedRectangle":{"isBackgroundTexture":true,"singleTextureOpacity":1,"textureType":1,"textBaseline":0,"textXHeight":0,"isVerticalText":false},"initialState":{"affineTransform":[1,0,0,1,0,0],"masksToBounds":false,"rotation":0,"scale":1,"position":{"pointX":960,"pointY":540},"width":1920,"sublayerTransform":[1,0,0,0,0,1,0,0,0,0,1,0,0,0,0,1],"contentsRect":{"y":0,"x":0,"width":1,"height":1},"opacity":1,"edgeAntialiasingMask":0,"height":1080,"hidden":false,"anchorPoint":{"pointX":0.5,"pointY":0.5}},"texture":"F060ECB2D3B13BDD8C493DD73E965B5C"}]}]},{"animations":[],"initialState":{"affineTransform":[1,0,0,1,0,0],"masksToBounds":false,"rotation":0,"scale":1,"position":{"pointX":960,"pointY":540},"width":1920,"sublayerTransform":[1,0,0,0,0,1,0,0,0,0,1,0,0,0,0,1],"contentsRect":{"y":0,"x":0,"width":1,"height":1},"opacity":1,"edgeAntialiasingMask":251658240,"height":1080,"hidden":false,"anchorPoint":{"pointX":0.5,"pointY":0.5}},"layers":[{"animations":[],"initialState":{"affineTransform":[1,0,0,1,0,0],"masksToBounds":false,"rotation":0,"scale":1,"position":{"pointX":961.49998389670304,"pointY":111.97106933606716},"width":1803,"sublayerTransform":[1,0,0,0,0,1,0,0,0,0,1,0,0,0,0,1],"contentsRect":{"y":0,"x":0,"width":1,"height":1},"opacity":1,"edgeAntialiasingMask":251658240,"height":6,"hidden":false,"anchorPoint":{"pointX":0.5,"pointY":0.5}},"layers":[{"animations":[],"layers":[],"texturedRectangle":{"singleTextureOpacity":1,"textXHeight":0,"shapePath":{"lineWidth":1,"flatness":0.59999999999999998,"lineCapStyle":0,"elements":[{"type":"MoveToPoint","points":[[2,3.000055268406868]]},{"type":"AddLine","points":[[1801.9998779296875,2.9710693359375]]}],"windingRule":0,"lineJoinStyle":0,"miterLimit":10},"isBackgroundTexture":true,"textBaseline":0,"isVerticalText":false,"textureType":5},"initialState":{"affineTransform":[1,0,0,1,0,0],"masksToBounds":false,"rotation":0,"scale":1,"position":{"pointX":899.50001610329696,"pointY":1.0289306639328402},"width":1803,"sublayerTransform":[1,0,0,0,0,1,0,0,0,0,1,0,0,0,0,1],"contentsRect":{"y":0,"x":0,"width":1,"height":1},"opacity":1,"edgeAntialiasingMask":0,"height":6,"hidden":false,"anchorPoint":{"pointX":0.5,"pointY":0.5}},"texture":"CC1D75045AACEAD3DAAE3D3B7654F275"}]}]},{"animations":[],"initialState":{"affineTransform":[1,0,0,1,0,0],"masksToBounds":false,"rotation":0,"scale":1,"position":{"pointX":960,"pointY":540},"width":1920,"sublayerTransform":[1,0,0,0,0,1,0,0,0,0,1,0,0,0,0,1],"contentsRect":{"y":0,"x":0,"width":1,"height":1},"opacity":1,"edgeAntialiasingMask":251658240,"height":1080,"hidden":false,"anchorPoint":{"pointX":0.5,"pointY":0.5}},"layers":[{"animations":[],"initialState":{"affineTransform":[1,0,0,1,0,0],"masksToBounds":false,"rotation":0,"scale":1,"position":{"pointX":226,"pointY":64.5},"width":332,"sublayerTransform":[1,0,0,0,0,1,0,0,0,0,1,0,0,0,0,1],"contentsRect":{"y":0,"x":0,"width":1,"height":1},"opacity":1,"edgeAntialiasingMask":251658240,"height":29,"hidden":false,"anchorPoint":{"pointX":0.5,"pointY":0.5}},"layers":[{"animations":[],"layers":[],"texturedRectangle":{"singleTextureOpacity":1,"textXHeight":0.89102909482758619,"textBaseline":0.92625269396551724,"isBackgroundTexture":true,"isVerticalText":false,"textColor":[0.83529406785964966,0.83529418706893921,0.83959966897964478,1],"textureType":6},"initialState":{"affineTransform":[1,0,0,1,0,0],"masksToBounds":false,"rotation":0,"scale":1,"position":{"pointX":169,"pointY":25.5},"width":332,"sublayerTransform":[1,0,0,0,0,1,0,0,0,0,1,0,0,0,0,1],"contentsRect":{"y":0,"x":0,"width":1,"height":1},"opacity":1,"edgeAntialiasingMask":0,"height":29,"hidden":false,"anchorPoint":{"pointX":0.5,"pointY":0.5}},"texture":"EFF14D30B06EA00E9E52AFFF50E90B03"}]}]},{"animations":[],"initialState":{"affineTransform":[1,0,0,1,0,0],"masksToBounds":false,"rotation":0,"scale":1,"position":{"pointX":960,"pointY":540},"width":1920,"sublayerTransform":[1,0,0,0,0,1,0,0,0,0,1,0,0,0,0,1],"contentsRect":{"y":0,"x":0,"width":1,"height":1},"opacity":1,"edgeAntialiasingMask":251658240,"height":1080,"hidden":false,"anchorPoint":{"pointX":0.5,"pointY":0.5}},"layers":[{"animations":[],"initialState":{"affineTransform":[1,0,0,1,0,0],"masksToBounds":false,"rotation":0,"scale":1,"position":{"pointX":150.5,"pointY":198},"width":181,"sublayerTransform":[1,0,0,0,0,1,0,0,0,0,1,0,0,0,0,1],"contentsRect":{"y":0,"x":0,"width":1,"height":1},"opacity":1,"edgeAntialiasingMask":251658240,"height":56,"hidden":false,"anchorPoint":{"pointX":0.5,"pointY":0.5}},"layers":[{"animations":[],"layers":[],"texturedRectangle":{"singleTextureOpacity":1,"textXHeight":0.65375839285714288,"textBaseline":0.96003831863403322,"isBackgroundTexture":true,"isVerticalText":false,"textColor":[0.2039216160774231,0.64705884456634521,0.85490202903747559,1],"textureType":6},"initialState":{"affineTransform":[1,0,0,1,0,0],"masksToBounds":false,"rotation":0,"scale":1,"position":{"pointX":93.5,"pointY":29},"width":181,"sublayerTransform":[1,0,0,0,0,1,0,0,0,0,1,0,0,0,0,1],"contentsRect":{"y":0,"x":0,"width":1,"height":1},"opacity":1,"edgeAntialiasingMask":0,"height":56,"hidden":false,"anchorPoint":{"pointX":0.5,"pointY":0.5}},"texture":"EA314A6407CB6C945B4C0DB198AACAF2"}]}]},{"animations":[],"initialState":{"affineTransform":[1,0,0,1,0,0],"masksToBounds":false,"rotation":0,"scale":1,"position":{"pointX":960,"pointY":540},"width":1920,"sublayerTransform":[1,0,0,0,0,1,0,0,0,0,1,0,0,0,0,1],"contentsRect":{"y":0,"x":0,"width":1,"height":1},"opacity":1,"edgeAntialiasingMask":251658240,"height":1080,"hidden":false,"anchorPoint":{"pointX":0.5,"pointY":0.5}},"layers":[{"animations":[],"initialState":{"affineTransform":[1,0,0,1,0,0],"masksToBounds":false,"rotation":0,"scale":1,"position":{"pointX":384,"pointY":539},"width":648,"sublayerTransform":[1,0,0,0,0,1,0,0,0,0,1,0,0,0,0,1],"contentsRect":{"y":0,"x":0,"width":1,"height":1},"opacity":1,"edgeAntialiasingMask":251658240,"height":470,"hidden":false,"anchorPoint":{"pointX":0.5,"pointY":0.5}},"objectID":"F3110F88-620E-4F0C-9883-9801311D1424","layers":[{"animations":[],"layers":[],"texturedRectangle":{"singleTextureOpacity":1,"textXHeight":0.55492682926829262,"textBaseline":0.9129787538109756,"isBackgroundTexture":false,"isVerticalText":false,"textColor":[0.83576232194900513,0.83576232194900513,0.83576232194900513,1],"textureType":6},"initialState":{"affineTransform":[1,0,0,1,0,0],"masksToBounds":false,"rotation":0,"scale":1,"position":{"pointX":167,"pointY":35.5},"width":310,"sublayerTransform":[1,0,0,0,0,1,0,0,0,0,1,0,0,0,0,1],"contentsRect":{"y":0,"x":0,"width":1,"height":1},"opacity":1,"edgeAntialiasingMask":0,"height":41,"hidden":true,"anchorPoint":{"pointX":0.5,"pointY":0.5}},"texture":"338FB3DAC9706D521D9A50392316EF03"},{"animations":[],"layers":[],"texturedRectangle":{"singleTextureOpacity":1,"textXHeight":0.44611764705882351,"textBaseline":0.75357115502450978,"isBackgroundTexture":false,"isVerticalText":false,"textColor":[0.83576232194900513,0.83576232194900513,0.83576232194900513,1],"textureType":6},"initialState":{"affineTransform":[1,0,0,1,0,0],"masksToBounds":false,"rotation":0,"scale":1,"position":{"pointX":272.5,"pointY":144.5},"width":521,"sublayerTransform":[1,0,0,0,0,1,0,0,0,0,1,0,0,0,0,1],"contentsRect":{"y":0,"x":0,"width":1,"height":1},"opacity":1,"edgeAntialiasingMask":0,"height":51,"hidden":true,"anchorPoint":{"pointX":0.5,"pointY":0.5}},"texture":"B91F7CE3C9C210F11E0B0C8265F67F38"},{"animations":[],"layers":[],"texturedRectangle":{"singleTextureOpacity":1,"textXHeight":0.45504,"textBaseline":0.74864257812500001,"isBackgroundTexture":false,"isVerticalText":false,"textColor":[0.83576232194900513,0.83576232194900513,0.83576232194900513,1],"textureType":6},"initialState":{"affineTransform":[1,0,0,1,0,0],"masksToBounds":false,"rotation":0,"scale":1,"position":{"pointX":244,"pointY":250},"width":464,"sublayerTransform":[1,0,0,0,0,1,0,0,0,0,1,0,0,0,0,1],"contentsRect":{"y":0,"x":0,"width":1,"height":1},"opacity":1,"edgeAntialiasingMask":0,"height":50,"hidden":true,"anchorPoint":{"pointX":0.5,"pointY":0.5}},"texture":"764AC2DAD017313B8416EA5D04A04BF8"},{"animations":[],"layers":[],"texturedRectangle":{"singleTextureOpacity":1,"textXHeight":0.58338461538461539,"textBaseline":0.90851612580128205,"isBackgroundTexture":false,"isVerticalText":false,"textColor":[0.83576232194900513,0.83576232194900513,0.83576232194900513,1],"textureType":6},"initialState":{"affineTransform":[1,0,0,1,0,0],"masksToBounds":false,"rotation":0,"scale":1,"position":{"pointX":100.5,"pointY":351.5},"width":177,"sublayerTransform":[1,0,0,0,0,1,0,0,0,0,1,0,0,0,0,1],"contentsRect":{"y":0,"x":0,"width":1,"height":1},"opacity":1,"edgeAntialiasingMask":0,"height":39,"hidden":true,"anchorPoint":{"pointX":0.5,"pointY":0.5}},"texture":"D6FDA76377A4B72BD709A19D5AB53409"},{"animations":[],"layers":[],"texturedRectangle":{"singleTextureOpacity":1,"textXHeight":0.45504,"textBaseline":0.74864257812500001,"isBackgroundTexture":false,"isVerticalText":false,"textColor":[0.83576232194900513,0.83576232194900513,0.83576232194900513,1],"textureType":6},"initialState":{"affineTransform":[1,0,0,1,0,0],"masksToBounds":false,"rotation":0,"scale":1,"position":{"pointX":336,"pointY":460},"width":648,"sublayerTransform":[1,0,0,0,0,1,0,0,0,0,1,0,0,0,0,1],"contentsRect":{"y":0,"x":0,"width":1,"height":1},"opacity":1,"edgeAntialiasingMask":0,"height":50,"hidden":true,"anchorPoint":{"pointX":0.5,"pointY":0.5}},"texture":"0418E1174A020D26EEBE5FA4772E2C44"}]}]}]}},{"effects":[{"beginTime":0,"baseLayer":{"animations":[],"initialState":{"affineTransform":[1,0,0,1,0,0],"masksToBounds":false,"rotation":0,"scale":1,"position":{"pointX":384,"pointY":539},"width":648,"sublayerTransform":[1,0,0,0,0,1,0,0,0,0,1,0,0,0,0,1],"contentsRect":{"y":0,"x":0,"width":1,"height":1},"opacity":1,"edgeAntialiasingMask":251658240,"height":470,"hidden":false,"anchorPoint":{"pointX":0.5,"pointY":0.5}},"objectID":"F3110F88-620E-4F0C-9883-9801311D1424","layers":[{"animations":[],"layers":[],"texturedRectangle":{"singleTextureOpacity":1,"textXHeight":0.55492682926829262,"textBaseline":0.9129787538109756,"isBackgroundTexture":false,"isVerticalText":false,"textColor":[0.83576232194900513,0.83576232194900513,0.83576232194900513,1],"textureType":6},"initialState":{"affineTransform":[1,0,0,1,0,0],"masksToBounds":false,"rotation":0,"scale":1,"position":{"pointX":167,"pointY":35.5},"width":310,"sublayerTransform":[1,0,0,0,0,1,0,0,0,0,1,0,0,0,0,1],"contentsRect":{"y":0,"x":0,"width":1,"height":1},"opacity":1,"edgeAntialiasingMask":0,"height":41,"hidden":false,"anchorPoint":{"pointX":0.5,"pointY":0.5}},"texture":"338FB3DAC9706D521D9A50392316EF03"},{"animations":[],"initialState":{"affineTransform":[1,0,0,1,0,0],"masksToBounds":false,"rotation":0,"scale":1,"position":{"pointX":900,"pointY":236},"width":648,"sublayerTransform":[1,0,0,0,0,1,0,0,0,0,1,-0.00035007912466775983,0,0,0,1],"contentsRect":{"y":0,"x":0,"width":1,"height":1},"opacity":1,"edgeAntialiasingMask":251658240,"height":470,"hidden":false,"anchorPoint":{"pointX":1.3888888888888888,"pointY":0.50212765957446803}},"layers":[{"animations":[{"additive":false,"timeOffset":0,"beginTime":1e-100,"repeatCount":0,"fillMode":"both","duration":0.001,"autoreverses":false,"animations":[{"additive":false,"timeOffset":0,"beginTime":0,"from":{"scalar":true},"repeatCount":0,"fillMode":"both","duration":0.0001,"autoreverses":false,"property":"hidden","to":{"scalar":false},"removedOnCompletion":true},{"additive":false,"timeOffset":0,"beginTime":0.0001,"from":{"scalar":false},"repeatCount":0,"fillMode":"forwards","duration":0.00089999999999999998,"autoreverses":false,"property":"hidden","to":{"scalar":false},"removedOnCompletion":true}],"removedOnCompletion":false}],"layers":[],"texturedRectangle":{"singleTextureOpacity":1,"textXHeight":0.44611764705882351,"textBaseline":0.75357115502450978,"isBackgroundTexture":false,"isVerticalText":false,"textColor":[0.83576232194900513,0.83576232194900513,0.83576232194900513,1],"textureType":6},"initialState":{"affineTransform":[1,0,0,1,0,0],"masksToBounds":false,"rotation":0,"scale":1,"position":{"pointX":272.5,"pointY":144.5},"width":521,"sublayerTransform":[1,0,0,0,0,1,0,0,0,0,1,0,0,0,0,1],"contentsRect":{"y":0,"x":0,"width":1,"height":1},"opacity":1,"edgeAntialiasingMask":0,"height":51,"hidden":true,"anchorPoint":{"pointX":0.5,"pointY":0.5}},"texture":"B91F7CE3C9C210F11E0B0C8265F67F38"}]},{"animations":[],"layers":[],"texturedRectangle":{"singleTextureOpacity":1,"textXHeight":0.45504,"textBaseline":0.74864257812500001,"isBackgroundTexture":false,"isVerticalText":false,"textColor":[0.83576232194900513,0.83576232194900513,0.83576232194900513,1],"textureType":6},"initialState":{"affineTransform":[1,0,0,1,0,0],"masksToBounds":false,"rotation":0,"scale":1,"position":{"pointX":244,"pointY":250},"width":464,"sublayerTransform":[1,0,0,0,0,1,0,0,0,0,1,0,0,0,0,1],"contentsRect":{"y":0,"x":0,"width":1,"height":1},"opacity":1,"edgeAntialiasingMask":0,"height":50,"hidden":true,"anchorPoint":{"pointX":0.5,"pointY":0.5}},"texture":"764AC2DAD017313B8416EA5D04A04BF8"},{"animations":[],"layers":[],"texturedRectangle":{"singleTextureOpacity":1,"textXHeight":0.58338461538461539,"textBaseline":0.90851612580128205,"isBackgroundTexture":false,"isVerticalText":false,"textColor":[0.83576232194900513,0.83576232194900513,0.83576232194900513,1],"textureType":6},"initialState":{"affineTransform":[1,0,0,1,0,0],"masksToBounds":false,"rotation":0,"scale":1,"position":{"pointX":100.5,"pointY":351.5},"width":177,"sublayerTransform":[1,0,0,0,0,1,0,0,0,0,1,0,0,0,0,1],"contentsRect":{"y":0,"x":0,"width":1,"height":1},"opacity":1,"edgeAntialiasingMask":0,"height":39,"hidden":true,"anchorPoint":{"pointX":0.5,"pointY":0.5}},"texture":"D6FDA76377A4B72BD709A19D5AB53409"},{"animations":[],"layers":[],"texturedRectangle":{"singleTextureOpacity":1,"textXHeight":0.45504,"textBaseline":0.74864257812500001,"isBackgroundTexture":false,"isVerticalText":false,"textColor":[0.83576232194900513,0.83576232194900513,0.83576232194900513,1],"textureType":6},"initialState":{"affineTransform":[1,0,0,1,0,0],"masksToBounds":false,"rotation":0,"scale":1,"position":{"pointX":336,"pointY":460},"width":648,"sublayerTransform":[1,0,0,0,0,1,0,0,0,0,1,0,0,0,0,1],"contentsRect":{"y":0,"x":0,"width":1,"height":1},"opacity":1,"edgeAntialiasingMask":0,"height":50,"hidden":true,"anchorPoint":{"pointX":0.5,"pointY":0.5}},"texture":"0418E1174A020D26EEBE5FA4772E2C44"}]},"effects":[],"duration":0.001,"type":"buildIn","attributes":{"direction":0},"name":"apple:bc-appear","objectID":"F3110F88-620E-4F0C-9883-9801311D1424"}],"automaticPlay":false,"hyperlinks":[],"accessibility":[{"text":"JoyFUL LOcal dev","targetRectangle":{"y":54,"x":64,"width":330.98554730415344,"height":42}},{"text":"Introduction","targetRectangle":{"y":308,"x":113.99999809265137,"width":270.096,"height":105}},{"text":"Agenda","targetRectangle":{"y":174,"x":64,"width":178.21427999999997,"height":71.558220367431659}}],"baseLayer":{"animations":[],"initialState":{"affineTransform":[1,0,0,1,0,0],"masksToBounds":false,"rotation":0,"scale":1,"position":{"pointX":960,"pointY":540},"width":1920,"sublayerTransform":[1,0,0,0,0,1,0,0,0,0,1,0,0,0,0,1],"contentsRect":{"y":0,"x":0,"width":1,"height":1},"opacity":1,"edgeAntialiasingMask":251658240,"height":1080,"hidden":false,"anchorPoint":{"pointX":0.5,"pointY":0.5}},"layers":[{"animations":[],"initialState":{"affineTransform":[1,0,0,1,0,0],"masksToBounds":false,"rotation":0,"scale":1,"position":{"pointX":960,"pointY":540},"width":1920,"sublayerTransform":[1,0,0,0,0,1,0,0,0,0,1,0,0,0,0,1],"contentsRect":{"y":0,"x":0,"width":1,"height":1},"opacity":1,"edgeAntialiasingMask":251658240,"height":1080,"hidden":false,"anchorPoint":{"pointX":0.5,"pointY":0.5}},"layers":[{"animations":[],"initialState":{"affineTransform":[1,0,0,1,0,0],"masksToBounds":false,"rotation":0,"scale":1,"position":{"pointX":960,"pointY":540},"width":1920,"sublayerTransform":[1,0,0,0,0,1,0,0,0,0,1,0,0,0,0,1],"contentsRect":{"y":0,"x":0,"width":1,"height":1},"opacity":1,"edgeAntialiasingMask":251658240,"height":1080,"hidden":false,"anchorPoint":{"pointX":0.5,"pointY":0.5}},"layers":[{"animations":[],"layers":[],"texturedRectangle":{"isBackgroundTexture":true,"singleTextureOpacity":1,"textureType":1,"textBaseline":0,"textXHeight":0,"isVerticalText":false},"initialState":{"affineTransform":[1,0,0,1,0,0],"masksToBounds":false,"rotation":0,"scale":1,"position":{"pointX":960,"pointY":540},"width":1920,"sublayerTransform":[1,0,0,0,0,1,0,0,0,0,1,0,0,0,0,1],"contentsRect":{"y":0,"x":0,"width":1,"height":1},"opacity":1,"edgeAntialiasingMask":0,"height":1080,"hidden":false,"anchorPoint":{"pointX":0.5,"pointY":0.5}},"texture":"F060ECB2D3B13BDD8C493DD73E965B5C"}]}]},{"animations":[],"initialState":{"affineTransform":[1,0,0,1,0,0],"masksToBounds":false,"rotation":0,"scale":1,"position":{"pointX":960,"pointY":540},"width":1920,"sublayerTransform":[1,0,0,0,0,1,0,0,0,0,1,0,0,0,0,1],"contentsRect":{"y":0,"x":0,"width":1,"height":1},"opacity":1,"edgeAntialiasingMask":251658240,"height":1080,"hidden":false,"anchorPoint":{"pointX":0.5,"pointY":0.5}},"layers":[{"animations":[],"initialState":{"affineTransform":[1,0,0,1,0,0],"masksToBounds":false,"rotation":0,"scale":1,"position":{"pointX":961.49998389670304,"pointY":111.97106933606716},"width":1803,"sublayerTransform":[1,0,0,0,0,1,0,0,0,0,1,0,0,0,0,1],"contentsRect":{"y":0,"x":0,"width":1,"height":1},"opacity":1,"edgeAntialiasingMask":251658240,"height":6,"hidden":false,"anchorPoint":{"pointX":0.5,"pointY":0.5}},"layers":[{"animations":[],"layers":[],"texturedRectangle":{"singleTextureOpacity":1,"textXHeight":0,"shapePath":{"lineWidth":1,"flatness":0.59999999999999998,"lineCapStyle":0,"elements":[{"type":"MoveToPoint","points":[[2,3.000055268406868]]},{"type":"AddLine","points":[[1801.9998779296875,2.9710693359375]]}],"windingRule":0,"lineJoinStyle":0,"miterLimit":10},"isBackgroundTexture":true,"textBaseline":0,"isVerticalText":false,"textureType":5},"initialState":{"affineTransform":[1,0,0,1,0,0],"masksToBounds":false,"rotation":0,"scale":1,"position":{"pointX":899.50001610329696,"pointY":1.0289306639328402},"width":1803,"sublayerTransform":[1,0,0,0,0,1,0,0,0,0,1,0,0,0,0,1],"contentsRect":{"y":0,"x":0,"width":1,"height":1},"opacity":1,"edgeAntialiasingMask":0,"height":6,"hidden":false,"anchorPoint":{"pointX":0.5,"pointY":0.5}},"texture":"CC1D75045AACEAD3DAAE3D3B7654F275"}]}]},{"animations":[],"initialState":{"affineTransform":[1,0,0,1,0,0],"masksToBounds":false,"rotation":0,"scale":1,"position":{"pointX":960,"pointY":540},"width":1920,"sublayerTransform":[1,0,0,0,0,1,0,0,0,0,1,0,0,0,0,1],"contentsRect":{"y":0,"x":0,"width":1,"height":1},"opacity":1,"edgeAntialiasingMask":251658240,"height":1080,"hidden":false,"anchorPoint":{"pointX":0.5,"pointY":0.5}},"layers":[{"animations":[],"initialState":{"affineTransform":[1,0,0,1,0,0],"masksToBounds":false,"rotation":0,"scale":1,"position":{"pointX":226,"pointY":64.5},"width":332,"sublayerTransform":[1,0,0,0,0,1,0,0,0,0,1,0,0,0,0,1],"contentsRect":{"y":0,"x":0,"width":1,"height":1},"opacity":1,"edgeAntialiasingMask":251658240,"height":29,"hidden":false,"anchorPoint":{"pointX":0.5,"pointY":0.5}},"layers":[{"animations":[],"layers":[],"texturedRectangle":{"singleTextureOpacity":1,"textXHeight":0.89102909482758619,"textBaseline":0.92625269396551724,"isBackgroundTexture":true,"isVerticalText":false,"textColor":[0.83529406785964966,0.83529418706893921,0.83959966897964478,1],"textureType":6},"initialState":{"affineTransform":[1,0,0,1,0,0],"masksToBounds":false,"rotation":0,"scale":1,"position":{"pointX":169,"pointY":25.5},"width":332,"sublayerTransform":[1,0,0,0,0,1,0,0,0,0,1,0,0,0,0,1],"contentsRect":{"y":0,"x":0,"width":1,"height":1},"opacity":1,"edgeAntialiasingMask":0,"height":29,"hidden":false,"anchorPoint":{"pointX":0.5,"pointY":0.5}},"texture":"EFF14D30B06EA00E9E52AFFF50E90B03"}]}]},{"animations":[],"initialState":{"affineTransform":[1,0,0,1,0,0],"masksToBounds":false,"rotation":0,"scale":1,"position":{"pointX":960,"pointY":540},"width":1920,"sublayerTransform":[1,0,0,0,0,1,0,0,0,0,1,0,0,0,0,1],"contentsRect":{"y":0,"x":0,"width":1,"height":1},"opacity":1,"edgeAntialiasingMask":251658240,"height":1080,"hidden":false,"anchorPoint":{"pointX":0.5,"pointY":0.5}},"layers":[{"animations":[],"initialState":{"affineTransform":[1,0,0,1,0,0],"masksToBounds":false,"rotation":0,"scale":1,"position":{"pointX":150.5,"pointY":198},"width":181,"sublayerTransform":[1,0,0,0,0,1,0,0,0,0,1,0,0,0,0,1],"contentsRect":{"y":0,"x":0,"width":1,"height":1},"opacity":1,"edgeAntialiasingMask":251658240,"height":56,"hidden":false,"anchorPoint":{"pointX":0.5,"pointY":0.5}},"layers":[{"animations":[],"layers":[],"texturedRectangle":{"singleTextureOpacity":1,"textXHeight":0.65375839285714288,"textBaseline":0.96003831863403322,"isBackgroundTexture":true,"isVerticalText":false,"textColor":[0.2039216160774231,0.64705884456634521,0.85490202903747559,1],"textureType":6},"initialState":{"affineTransform":[1,0,0,1,0,0],"masksToBounds":false,"rotation":0,"scale":1,"position":{"pointX":93.5,"pointY":29},"width":181,"sublayerTransform":[1,0,0,0,0,1,0,0,0,0,1,0,0,0,0,1],"contentsRect":{"y":0,"x":0,"width":1,"height":1},"opacity":1,"edgeAntialiasingMask":0,"height":56,"hidden":false,"anchorPoint":{"pointX":0.5,"pointY":0.5}},"texture":"EA314A6407CB6C945B4C0DB198AACAF2"}]}]},{"animations":[],"initialState":{"affineTransform":[1,0,0,1,0,0],"masksToBounds":false,"rotation":0,"scale":1,"position":{"pointX":960,"pointY":540},"width":1920,"sublayerTransform":[1,0,0,0,0,1,0,0,0,0,1,0,0,0,0,1],"contentsRect":{"y":0,"x":0,"width":1,"height":1},"opacity":1,"edgeAntialiasingMask":251658240,"height":1080,"hidden":false,"anchorPoint":{"pointX":0.5,"pointY":0.5}},"layers":[{"animations":[],"initialState":{"affineTransform":[1,0,0,1,0,0],"masksToBounds":false,"rotation":0,"scale":1,"position":{"pointX":384,"pointY":539},"width":648,"sublayerTransform":[1,0,0,0,0,1,0,0,0,0,1,0,0,0,0,1],"contentsRect":{"y":0,"x":0,"width":1,"height":1},"opacity":1,"edgeAntialiasingMask":251658240,"height":470,"hidden":false,"anchorPoint":{"pointX":0.5,"pointY":0.5}},"objectID":"F3110F88-620E-4F0C-9883-9801311D1424","layers":[{"animations":[],"layers":[],"texturedRectangle":{"singleTextureOpacity":1,"textXHeight":0.55492682926829262,"textBaseline":0.9129787538109756,"isBackgroundTexture":false,"isVerticalText":false,"textColor":[0.83576232194900513,0.83576232194900513,0.83576232194900513,1],"textureType":6},"initialState":{"affineTransform":[1,0,0,1,0,0],"masksToBounds":false,"rotation":0,"scale":1,"position":{"pointX":167,"pointY":35.5},"width":310,"sublayerTransform":[1,0,0,0,0,1,0,0,0,0,1,0,0,0,0,1],"contentsRect":{"y":0,"x":0,"width":1,"height":1},"opacity":1,"edgeAntialiasingMask":0,"height":41,"hidden":false,"anchorPoint":{"pointX":0.5,"pointY":0.5}},"texture":"338FB3DAC9706D521D9A50392316EF03"},{"animations":[],"layers":[],"texturedRectangle":{"singleTextureOpacity":1,"textXHeight":0.44611764705882351,"textBaseline":0.75357115502450978,"isBackgroundTexture":false,"isVerticalText":false,"textColor":[0.83576232194900513,0.83576232194900513,0.83576232194900513,1],"textureType":6},"initialState":{"affineTransform":[1,0,0,1,0,0],"masksToBounds":false,"rotation":0,"scale":1,"position":{"pointX":272.5,"pointY":144.5},"width":521,"sublayerTransform":[1,0,0,0,0,1,0,0,0,0,1,0,0,0,0,1],"contentsRect":{"y":0,"x":0,"width":1,"height":1},"opacity":1,"edgeAntialiasingMask":0,"height":51,"hidden":true,"anchorPoint":{"pointX":0.5,"pointY":0.5}},"texture":"B91F7CE3C9C210F11E0B0C8265F67F38"},{"animations":[],"layers":[],"texturedRectangle":{"singleTextureOpacity":1,"textXHeight":0.45504,"textBaseline":0.74864257812500001,"isBackgroundTexture":false,"isVerticalText":false,"textColor":[0.83576232194900513,0.83576232194900513,0.83576232194900513,1],"textureType":6},"initialState":{"affineTransform":[1,0,0,1,0,0],"masksToBounds":false,"rotation":0,"scale":1,"position":{"pointX":244,"pointY":250},"width":464,"sublayerTransform":[1,0,0,0,0,1,0,0,0,0,1,0,0,0,0,1],"contentsRect":{"y":0,"x":0,"width":1,"height":1},"opacity":1,"edgeAntialiasingMask":0,"height":50,"hidden":true,"anchorPoint":{"pointX":0.5,"pointY":0.5}},"texture":"764AC2DAD017313B8416EA5D04A04BF8"},{"animations":[],"layers":[],"texturedRectangle":{"singleTextureOpacity":1,"textXHeight":0.58338461538461539,"textBaseline":0.90851612580128205,"isBackgroundTexture":false,"isVerticalText":false,"textColor":[0.83576232194900513,0.83576232194900513,0.83576232194900513,1],"textureType":6},"initialState":{"affineTransform":[1,0,0,1,0,0],"masksToBounds":false,"rotation":0,"scale":1,"position":{"pointX":100.5,"pointY":351.5},"width":177,"sublayerTransform":[1,0,0,0,0,1,0,0,0,0,1,0,0,0,0,1],"contentsRect":{"y":0,"x":0,"width":1,"height":1},"opacity":1,"edgeAntialiasingMask":0,"height":39,"hidden":true,"anchorPoint":{"pointX":0.5,"pointY":0.5}},"texture":"D6FDA76377A4B72BD709A19D5AB53409"},{"animations":[],"layers":[],"texturedRectangle":{"singleTextureOpacity":1,"textXHeight":0.45504,"textBaseline":0.74864257812500001,"isBackgroundTexture":false,"isVerticalText":false,"textColor":[0.83576232194900513,0.83576232194900513,0.83576232194900513,1],"textureType":6},"initialState":{"affineTransform":[1,0,0,1,0,0],"masksToBounds":false,"rotation":0,"scale":1,"position":{"pointX":336,"pointY":460},"width":648,"sublayerTransform":[1,0,0,0,0,1,0,0,0,0,1,0,0,0,0,1],"contentsRect":{"y":0,"x":0,"width":1,"height":1},"opacity":1,"edgeAntialiasingMask":0,"height":50,"hidden":true,"anchorPoint":{"pointX":0.5,"pointY":0.5}},"texture":"0418E1174A020D26EEBE5FA4772E2C44"}]}]}]}},{"effects":[{"beginTime":0,"baseLayer":{"animations":[],"initialState":{"affineTransform":[1,0,0,1,0,0],"masksToBounds":false,"rotation":0,"scale":1,"position":{"pointX":384,"pointY":539},"width":648,"sublayerTransform":[1,0,0,0,0,1,0,0,0,0,1,0,0,0,0,1],"contentsRect":{"y":0,"x":0,"width":1,"height":1},"opacity":1,"edgeAntialiasingMask":251658240,"height":470,"hidden":false,"anchorPoint":{"pointX":0.5,"pointY":0.5}},"objectID":"F3110F88-620E-4F0C-9883-9801311D1424","layers":[{"animations":[],"layers":[],"texturedRectangle":{"singleTextureOpacity":1,"textXHeight":0.55492682926829262,"textBaseline":0.9129787538109756,"isBackgroundTexture":false,"isVerticalText":false,"textColor":[0.83576232194900513,0.83576232194900513,0.83576232194900513,1],"textureType":6},"initialState":{"affineTransform":[1,0,0,1,0,0],"masksToBounds":false,"rotation":0,"scale":1,"position":{"pointX":167,"pointY":35.5},"width":310,"sublayerTransform":[1,0,0,0,0,1,0,0,0,0,1,0,0,0,0,1],"contentsRect":{"y":0,"x":0,"width":1,"height":1},"opacity":1,"edgeAntialiasingMask":0,"height":41,"hidden":false,"anchorPoint":{"pointX":0.5,"pointY":0.5}},"texture":"338FB3DAC9706D521D9A50392316EF03"},{"animations":[],"layers":[],"texturedRectangle":{"singleTextureOpacity":1,"textXHeight":0.44611764705882351,"textBaseline":0.75357115502450978,"isBackgroundTexture":false,"isVerticalText":false,"textColor":[0.83576232194900513,0.83576232194900513,0.83576232194900513,1],"textureType":6},"initialState":{"affineTransform":[1,0,0,1,0,0],"masksToBounds":false,"rotation":0,"scale":1,"position":{"pointX":272.5,"pointY":144.5},"width":521,"sublayerTransform":[1,0,0,0,0,1,0,0,0,0,1,0,0,0,0,1],"contentsRect":{"y":0,"x":0,"width":1,"height":1},"opacity":1,"edgeAntialiasingMask":0,"height":51,"hidden":false,"anchorPoint":{"pointX":0.5,"pointY":0.5}},"texture":"B91F7CE3C9C210F11E0B0C8265F67F38"},{"animations":[],"initialState":{"affineTransform":[1,0,0,1,0,0],"masksToBounds":false,"rotation":0,"scale":1,"position":{"pointX":900,"pointY":236},"width":648,"sublayerTransform":[1,0,0,0,0,1,0,0,0,0,1,-0.00035007912466775983,0,0,0,1],"contentsRect":{"y":0,"x":0,"width":1,"height":1},"opacity":1,"edgeAntialiasingMask":251658240,"height":470,"hidden":false,"anchorPoint":{"pointX":1.3888888888888888,"pointY":0.50212765957446803}},"layers":[{"animations":[{"additive":false,"timeOffset":0,"beginTime":1e-100,"repeatCount":0,"fillMode":"both","duration":0.001,"autoreverses":false,"animations":[{"additive":false,"timeOffset":0,"beginTime":0,"from":{"scalar":true},"repeatCount":0,"fillMode":"both","duration":0.0001,"autoreverses":false,"property":"hidden","to":{"scalar":false},"removedOnCompletion":true},{"additive":false,"timeOffset":0,"beginTime":0.0001,"from":{"scalar":false},"repeatCount":0,"fillMode":"forwards","duration":0.00089999999999999998,"autoreverses":false,"property":"hidden","to":{"scalar":false},"removedOnCompletion":true}],"removedOnCompletion":false}],"layers":[],"texturedRectangle":{"singleTextureOpacity":1,"textXHeight":0.45504,"textBaseline":0.74864257812500001,"isBackgroundTexture":false,"isVerticalText":false,"textColor":[0.83576232194900513,0.83576232194900513,0.83576232194900513,1],"textureType":6},"initialState":{"affineTransform":[1,0,0,1,0,0],"masksToBounds":false,"rotation":0,"scale":1,"position":{"pointX":244,"pointY":250},"width":464,"sublayerTransform":[1,0,0,0,0,1,0,0,0,0,1,0,0,0,0,1],"contentsRect":{"y":0,"x":0,"width":1,"height":1},"opacity":1,"edgeAntialiasingMask":0,"height":50,"hidden":true,"anchorPoint":{"pointX":0.5,"pointY":0.5}},"texture":"764AC2DAD017313B8416EA5D04A04BF8"}]},{"animations":[],"layers":[],"texturedRectangle":{"singleTextureOpacity":1,"textXHeight":0.58338461538461539,"textBaseline":0.90851612580128205,"isBackgroundTexture":false,"isVerticalText":false,"textColor":[0.83576232194900513,0.83576232194900513,0.83576232194900513,1],"textureType":6},"initialState":{"affineTransform":[1,0,0,1,0,0],"masksToBounds":false,"rotation":0,"scale":1,"position":{"pointX":100.5,"pointY":351.5},"width":177,"sublayerTransform":[1,0,0,0,0,1,0,0,0,0,1,0,0,0,0,1],"contentsRect":{"y":0,"x":0,"width":1,"height":1},"opacity":1,"edgeAntialiasingMask":0,"height":39,"hidden":true,"anchorPoint":{"pointX":0.5,"pointY":0.5}},"texture":"D6FDA76377A4B72BD709A19D5AB53409"},{"animations":[],"layers":[],"texturedRectangle":{"singleTextureOpacity":1,"textXHeight":0.45504,"textBaseline":0.74864257812500001,"isBackgroundTexture":false,"isVerticalText":false,"textColor":[0.83576232194900513,0.83576232194900513,0.83576232194900513,1],"textureType":6},"initialState":{"affineTransform":[1,0,0,1,0,0],"masksToBounds":false,"rotation":0,"scale":1,"position":{"pointX":336,"pointY":460},"width":648,"sublayerTransform":[1,0,0,0,0,1,0,0,0,0,1,0,0,0,0,1],"contentsRect":{"y":0,"x":0,"width":1,"height":1},"opacity":1,"edgeAntialiasingMask":0,"height":50,"hidden":true,"anchorPoint":{"pointX":0.5,"pointY":0.5}},"texture":"0418E1174A020D26EEBE5FA4772E2C44"}]},"effects":[],"duration":0.001,"type":"buildIn","attributes":{"direction":0},"name":"apple:bc-appear","objectID":"F3110F88-620E-4F0C-9883-9801311D1424"}],"automaticPlay":false,"hyperlinks":[],"accessibility":[{"text":"JoyFUL LOcal dev","targetRectangle":{"y":54,"x":64,"width":330.98554730415344,"height":42}},{"text":"Introduction","targetRectangle":{"y":308,"x":113.99999809265137,"width":270.096,"height":105}},{"text":"“Joyful Local Dev” ???","targetRectangle":{"y":413,"x":113.99999809265137,"width":479.03999999999996,"height":105}},{"text":"Agenda","targetRectangle":{"y":174,"x":64,"width":178.21427999999997,"height":71.558220367431659}}],"baseLayer":{"animations":[],"initialState":{"affineTransform":[1,0,0,1,0,0],"masksToBounds":false,"rotation":0,"scale":1,"position":{"pointX":960,"pointY":540},"width":1920,"sublayerTransform":[1,0,0,0,0,1,0,0,0,0,1,0,0,0,0,1],"contentsRect":{"y":0,"x":0,"width":1,"height":1},"opacity":1,"edgeAntialiasingMask":251658240,"height":1080,"hidden":false,"anchorPoint":{"pointX":0.5,"pointY":0.5}},"layers":[{"animations":[],"initialState":{"affineTransform":[1,0,0,1,0,0],"masksToBounds":false,"rotation":0,"scale":1,"position":{"pointX":960,"pointY":540},"width":1920,"sublayerTransform":[1,0,0,0,0,1,0,0,0,0,1,0,0,0,0,1],"contentsRect":{"y":0,"x":0,"width":1,"height":1},"opacity":1,"edgeAntialiasingMask":251658240,"height":1080,"hidden":false,"anchorPoint":{"pointX":0.5,"pointY":0.5}},"layers":[{"animations":[],"initialState":{"affineTransform":[1,0,0,1,0,0],"masksToBounds":false,"rotation":0,"scale":1,"position":{"pointX":960,"pointY":540},"width":1920,"sublayerTransform":[1,0,0,0,0,1,0,0,0,0,1,0,0,0,0,1],"contentsRect":{"y":0,"x":0,"width":1,"height":1},"opacity":1,"edgeAntialiasingMask":251658240,"height":1080,"hidden":false,"anchorPoint":{"pointX":0.5,"pointY":0.5}},"layers":[{"animations":[],"layers":[],"texturedRectangle":{"isBackgroundTexture":true,"singleTextureOpacity":1,"textureType":1,"textBaseline":0,"textXHeight":0,"isVerticalText":false},"initialState":{"affineTransform":[1,0,0,1,0,0],"masksToBounds":false,"rotation":0,"scale":1,"position":{"pointX":960,"pointY":540},"width":1920,"sublayerTransform":[1,0,0,0,0,1,0,0,0,0,1,0,0,0,0,1],"contentsRect":{"y":0,"x":0,"width":1,"height":1},"opacity":1,"edgeAntialiasingMask":0,"height":1080,"hidden":false,"anchorPoint":{"pointX":0.5,"pointY":0.5}},"texture":"F060ECB2D3B13BDD8C493DD73E965B5C"}]}]},{"animations":[],"initialState":{"affineTransform":[1,0,0,1,0,0],"masksToBounds":false,"rotation":0,"scale":1,"position":{"pointX":960,"pointY":540},"width":1920,"sublayerTransform":[1,0,0,0,0,1,0,0,0,0,1,0,0,0,0,1],"contentsRect":{"y":0,"x":0,"width":1,"height":1},"opacity":1,"edgeAntialiasingMask":251658240,"height":1080,"hidden":false,"anchorPoint":{"pointX":0.5,"pointY":0.5}},"layers":[{"animations":[],"initialState":{"affineTransform":[1,0,0,1,0,0],"masksToBounds":false,"rotation":0,"scale":1,"position":{"pointX":961.49998389670304,"pointY":111.97106933606716},"width":1803,"sublayerTransform":[1,0,0,0,0,1,0,0,0,0,1,0,0,0,0,1],"contentsRect":{"y":0,"x":0,"width":1,"height":1},"opacity":1,"edgeAntialiasingMask":251658240,"height":6,"hidden":false,"anchorPoint":{"pointX":0.5,"pointY":0.5}},"layers":[{"animations":[],"layers":[],"texturedRectangle":{"singleTextureOpacity":1,"textXHeight":0,"shapePath":{"lineWidth":1,"flatness":0.59999999999999998,"lineCapStyle":0,"elements":[{"type":"MoveToPoint","points":[[2,3.000055268406868]]},{"type":"AddLine","points":[[1801.9998779296875,2.9710693359375]]}],"windingRule":0,"lineJoinStyle":0,"miterLimit":10},"isBackgroundTexture":true,"textBaseline":0,"isVerticalText":false,"textureType":5},"initialState":{"affineTransform":[1,0,0,1,0,0],"masksToBounds":false,"rotation":0,"scale":1,"position":{"pointX":899.50001610329696,"pointY":1.0289306639328402},"width":1803,"sublayerTransform":[1,0,0,0,0,1,0,0,0,0,1,0,0,0,0,1],"contentsRect":{"y":0,"x":0,"width":1,"height":1},"opacity":1,"edgeAntialiasingMask":0,"height":6,"hidden":false,"anchorPoint":{"pointX":0.5,"pointY":0.5}},"texture":"CC1D75045AACEAD3DAAE3D3B7654F275"}]}]},{"animations":[],"initialState":{"affineTransform":[1,0,0,1,0,0],"masksToBounds":false,"rotation":0,"scale":1,"position":{"pointX":960,"pointY":540},"width":1920,"sublayerTransform":[1,0,0,0,0,1,0,0,0,0,1,0,0,0,0,1],"contentsRect":{"y":0,"x":0,"width":1,"height":1},"opacity":1,"edgeAntialiasingMask":251658240,"height":1080,"hidden":false,"anchorPoint":{"pointX":0.5,"pointY":0.5}},"layers":[{"animations":[],"initialState":{"affineTransform":[1,0,0,1,0,0],"masksToBounds":false,"rotation":0,"scale":1,"position":{"pointX":226,"pointY":64.5},"width":332,"sublayerTransform":[1,0,0,0,0,1,0,0,0,0,1,0,0,0,0,1],"contentsRect":{"y":0,"x":0,"width":1,"height":1},"opacity":1,"edgeAntialiasingMask":251658240,"height":29,"hidden":false,"anchorPoint":{"pointX":0.5,"pointY":0.5}},"layers":[{"animations":[],"layers":[],"texturedRectangle":{"singleTextureOpacity":1,"textXHeight":0.89102909482758619,"textBaseline":0.92625269396551724,"isBackgroundTexture":true,"isVerticalText":false,"textColor":[0.83529406785964966,0.83529418706893921,0.83959966897964478,1],"textureType":6},"initialState":{"affineTransform":[1,0,0,1,0,0],"masksToBounds":false,"rotation":0,"scale":1,"position":{"pointX":169,"pointY":25.5},"width":332,"sublayerTransform":[1,0,0,0,0,1,0,0,0,0,1,0,0,0,0,1],"contentsRect":{"y":0,"x":0,"width":1,"height":1},"opacity":1,"edgeAntialiasingMask":0,"height":29,"hidden":false,"anchorPoint":{"pointX":0.5,"pointY":0.5}},"texture":"EFF14D30B06EA00E9E52AFFF50E90B03"}]}]},{"animations":[],"initialState":{"affineTransform":[1,0,0,1,0,0],"masksToBounds":false,"rotation":0,"scale":1,"position":{"pointX":960,"pointY":540},"width":1920,"sublayerTransform":[1,0,0,0,0,1,0,0,0,0,1,0,0,0,0,1],"contentsRect":{"y":0,"x":0,"width":1,"height":1},"opacity":1,"edgeAntialiasingMask":251658240,"height":1080,"hidden":false,"anchorPoint":{"pointX":0.5,"pointY":0.5}},"layers":[{"animations":[],"initialState":{"affineTransform":[1,0,0,1,0,0],"masksToBounds":false,"rotation":0,"scale":1,"position":{"pointX":150.5,"pointY":198},"width":181,"sublayerTransform":[1,0,0,0,0,1,0,0,0,0,1,0,0,0,0,1],"contentsRect":{"y":0,"x":0,"width":1,"height":1},"opacity":1,"edgeAntialiasingMask":251658240,"height":56,"hidden":false,"anchorPoint":{"pointX":0.5,"pointY":0.5}},"layers":[{"animations":[],"layers":[],"texturedRectangle":{"singleTextureOpacity":1,"textXHeight":0.65375839285714288,"textBaseline":0.96003831863403322,"isBackgroundTexture":true,"isVerticalText":false,"textColor":[0.2039216160774231,0.64705884456634521,0.85490202903747559,1],"textureType":6},"initialState":{"affineTransform":[1,0,0,1,0,0],"masksToBounds":false,"rotation":0,"scale":1,"position":{"pointX":93.5,"pointY":29},"width":181,"sublayerTransform":[1,0,0,0,0,1,0,0,0,0,1,0,0,0,0,1],"contentsRect":{"y":0,"x":0,"width":1,"height":1},"opacity":1,"edgeAntialiasingMask":0,"height":56,"hidden":false,"anchorPoint":{"pointX":0.5,"pointY":0.5}},"texture":"EA314A6407CB6C945B4C0DB198AACAF2"}]}]},{"animations":[],"initialState":{"affineTransform":[1,0,0,1,0,0],"masksToBounds":false,"rotation":0,"scale":1,"position":{"pointX":960,"pointY":540},"width":1920,"sublayerTransform":[1,0,0,0,0,1,0,0,0,0,1,0,0,0,0,1],"contentsRect":{"y":0,"x":0,"width":1,"height":1},"opacity":1,"edgeAntialiasingMask":251658240,"height":1080,"hidden":false,"anchorPoint":{"pointX":0.5,"pointY":0.5}},"layers":[{"animations":[],"initialState":{"affineTransform":[1,0,0,1,0,0],"masksToBounds":false,"rotation":0,"scale":1,"position":{"pointX":384,"pointY":539},"width":648,"sublayerTransform":[1,0,0,0,0,1,0,0,0,0,1,0,0,0,0,1],"contentsRect":{"y":0,"x":0,"width":1,"height":1},"opacity":1,"edgeAntialiasingMask":251658240,"height":470,"hidden":false,"anchorPoint":{"pointX":0.5,"pointY":0.5}},"objectID":"F3110F88-620E-4F0C-9883-9801311D1424","layers":[{"animations":[],"layers":[],"texturedRectangle":{"singleTextureOpacity":1,"textXHeight":0.55492682926829262,"textBaseline":0.9129787538109756,"isBackgroundTexture":false,"isVerticalText":false,"textColor":[0.83576232194900513,0.83576232194900513,0.83576232194900513,1],"textureType":6},"initialState":{"affineTransform":[1,0,0,1,0,0],"masksToBounds":false,"rotation":0,"scale":1,"position":{"pointX":167,"pointY":35.5},"width":310,"sublayerTransform":[1,0,0,0,0,1,0,0,0,0,1,0,0,0,0,1],"contentsRect":{"y":0,"x":0,"width":1,"height":1},"opacity":1,"edgeAntialiasingMask":0,"height":41,"hidden":false,"anchorPoint":{"pointX":0.5,"pointY":0.5}},"texture":"338FB3DAC9706D521D9A50392316EF03"},{"animations":[],"layers":[],"texturedRectangle":{"singleTextureOpacity":1,"textXHeight":0.44611764705882351,"textBaseline":0.75357115502450978,"isBackgroundTexture":false,"isVerticalText":false,"textColor":[0.83576232194900513,0.83576232194900513,0.83576232194900513,1],"textureType":6},"initialState":{"affineTransform":[1,0,0,1,0,0],"masksToBounds":false,"rotation":0,"scale":1,"position":{"pointX":272.5,"pointY":144.5},"width":521,"sublayerTransform":[1,0,0,0,0,1,0,0,0,0,1,0,0,0,0,1],"contentsRect":{"y":0,"x":0,"width":1,"height":1},"opacity":1,"edgeAntialiasingMask":0,"height":51,"hidden":false,"anchorPoint":{"pointX":0.5,"pointY":0.5}},"texture":"B91F7CE3C9C210F11E0B0C8265F67F38"},{"animations":[],"layers":[],"texturedRectangle":{"singleTextureOpacity":1,"textXHeight":0.45504,"textBaseline":0.74864257812500001,"isBackgroundTexture":false,"isVerticalText":false,"textColor":[0.83576232194900513,0.83576232194900513,0.83576232194900513,1],"textureType":6},"initialState":{"affineTransform":[1,0,0,1,0,0],"masksToBounds":false,"rotation":0,"scale":1,"position":{"pointX":244,"pointY":250},"width":464,"sublayerTransform":[1,0,0,0,0,1,0,0,0,0,1,0,0,0,0,1],"contentsRect":{"y":0,"x":0,"width":1,"height":1},"opacity":1,"edgeAntialiasingMask":0,"height":50,"hidden":true,"anchorPoint":{"pointX":0.5,"pointY":0.5}},"texture":"764AC2DAD017313B8416EA5D04A04BF8"},{"animations":[],"layers":[],"texturedRectangle":{"singleTextureOpacity":1,"textXHeight":0.58338461538461539,"textBaseline":0.90851612580128205,"isBackgroundTexture":false,"isVerticalText":false,"textColor":[0.83576232194900513,0.83576232194900513,0.83576232194900513,1],"textureType":6},"initialState":{"affineTransform":[1,0,0,1,0,0],"masksToBounds":false,"rotation":0,"scale":1,"position":{"pointX":100.5,"pointY":351.5},"width":177,"sublayerTransform":[1,0,0,0,0,1,0,0,0,0,1,0,0,0,0,1],"contentsRect":{"y":0,"x":0,"width":1,"height":1},"opacity":1,"edgeAntialiasingMask":0,"height":39,"hidden":true,"anchorPoint":{"pointX":0.5,"pointY":0.5}},"texture":"D6FDA76377A4B72BD709A19D5AB53409"},{"animations":[],"layers":[],"texturedRectangle":{"singleTextureOpacity":1,"textXHeight":0.45504,"textBaseline":0.74864257812500001,"isBackgroundTexture":false,"isVerticalText":false,"textColor":[0.83576232194900513,0.83576232194900513,0.83576232194900513,1],"textureType":6},"initialState":{"affineTransform":[1,0,0,1,0,0],"masksToBounds":false,"rotation":0,"scale":1,"position":{"pointX":336,"pointY":460},"width":648,"sublayerTransform":[1,0,0,0,0,1,0,0,0,0,1,0,0,0,0,1],"contentsRect":{"y":0,"x":0,"width":1,"height":1},"opacity":1,"edgeAntialiasingMask":0,"height":50,"hidden":true,"anchorPoint":{"pointX":0.5,"pointY":0.5}},"texture":"0418E1174A020D26EEBE5FA4772E2C44"}]}]}]}},{"effects":[{"beginTime":0,"baseLayer":{"animations":[],"initialState":{"affineTransform":[1,0,0,1,0,0],"masksToBounds":false,"rotation":0,"scale":1,"position":{"pointX":384,"pointY":539},"width":648,"sublayerTransform":[1,0,0,0,0,1,0,0,0,0,1,0,0,0,0,1],"contentsRect":{"y":0,"x":0,"width":1,"height":1},"opacity":1,"edgeAntialiasingMask":251658240,"height":470,"hidden":false,"anchorPoint":{"pointX":0.5,"pointY":0.5}},"objectID":"F3110F88-620E-4F0C-9883-9801311D1424","layers":[{"animations":[],"layers":[],"texturedRectangle":{"singleTextureOpacity":1,"textXHeight":0.55492682926829262,"textBaseline":0.9129787538109756,"isBackgroundTexture":false,"isVerticalText":false,"textColor":[0.83576232194900513,0.83576232194900513,0.83576232194900513,1],"textureType":6},"initialState":{"affineTransform":[1,0,0,1,0,0],"masksToBounds":false,"rotation":0,"scale":1,"position":{"pointX":167,"pointY":35.5},"width":310,"sublayerTransform":[1,0,0,0,0,1,0,0,0,0,1,0,0,0,0,1],"contentsRect":{"y":0,"x":0,"width":1,"height":1},"opacity":1,"edgeAntialiasingMask":0,"height":41,"hidden":false,"anchorPoint":{"pointX":0.5,"pointY":0.5}},"texture":"338FB3DAC9706D521D9A50392316EF03"},{"animations":[],"layers":[],"texturedRectangle":{"singleTextureOpacity":1,"textXHeight":0.44611764705882351,"textBaseline":0.75357115502450978,"isBackgroundTexture":false,"isVerticalText":false,"textColor":[0.83576232194900513,0.83576232194900513,0.83576232194900513,1],"textureType":6},"initialState":{"affineTransform":[1,0,0,1,0,0],"masksToBounds":false,"rotation":0,"scale":1,"position":{"pointX":272.5,"pointY":144.5},"width":521,"sublayerTransform":[1,0,0,0,0,1,0,0,0,0,1,0,0,0,0,1],"contentsRect":{"y":0,"x":0,"width":1,"height":1},"opacity":1,"edgeAntialiasingMask":0,"height":51,"hidden":false,"anchorPoint":{"pointX":0.5,"pointY":0.5}},"texture":"B91F7CE3C9C210F11E0B0C8265F67F38"},{"animations":[],"layers":[],"texturedRectangle":{"singleTextureOpacity":1,"textXHeight":0.45504,"textBaseline":0.74864257812500001,"isBackgroundTexture":false,"isVerticalText":false,"textColor":[0.83576232194900513,0.83576232194900513,0.83576232194900513,1],"textureType":6},"initialState":{"affineTransform":[1,0,0,1,0,0],"masksToBounds":false,"rotation":0,"scale":1,"position":{"pointX":244,"pointY":250},"width":464,"sublayerTransform":[1,0,0,0,0,1,0,0,0,0,1,0,0,0,0,1],"contentsRect":{"y":0,"x":0,"width":1,"height":1},"opacity":1,"edgeAntialiasingMask":0,"height":50,"hidden":false,"anchorPoint":{"pointX":0.5,"pointY":0.5}},"texture":"764AC2DAD017313B8416EA5D04A04BF8"},{"animations":[],"initialState":{"affineTransform":[1,0,0,1,0,0],"masksToBounds":false,"rotation":0,"scale":1,"position":{"pointX":900,"pointY":236},"width":648,"sublayerTransform":[1,0,0,0,0,1,0,0,0,0,1,-0.00035007912466775983,0,0,0,1],"contentsRect":{"y":0,"x":0,"width":1,"height":1},"opacity":1,"edgeAntialiasingMask":251658240,"height":470,"hidden":false,"anchorPoint":{"pointX":1.3888888888888888,"pointY":0.50212765957446803}},"layers":[{"animations":[{"additive":false,"timeOffset":0,"beginTime":1e-100,"repeatCount":0,"fillMode":"both","duration":0.001,"autoreverses":false,"animations":[{"additive":false,"timeOffset":0,"beginTime":0,"from":{"scalar":true},"repeatCount":0,"fillMode":"both","duration":0.0001,"autoreverses":false,"property":"hidden","to":{"scalar":false},"removedOnCompletion":true},{"additive":false,"timeOffset":0,"beginTime":0.0001,"from":{"scalar":false},"repeatCount":0,"fillMode":"forwards","duration":0.00089999999999999998,"autoreverses":false,"property":"hidden","to":{"scalar":false},"removedOnCompletion":true}],"removedOnCompletion":false}],"layers":[],"texturedRectangle":{"singleTextureOpacity":1,"textXHeight":0.58338461538461539,"textBaseline":0.90851612580128205,"isBackgroundTexture":false,"isVerticalText":false,"textColor":[0.83576232194900513,0.83576232194900513,0.83576232194900513,1],"textureType":6},"initialState":{"affineTransform":[1,0,0,1,0,0],"masksToBounds":false,"rotation":0,"scale":1,"position":{"pointX":100.5,"pointY":351.5},"width":177,"sublayerTransform":[1,0,0,0,0,1,0,0,0,0,1,0,0,0,0,1],"contentsRect":{"y":0,"x":0,"width":1,"height":1},"opacity":1,"edgeAntialiasingMask":0,"height":39,"hidden":true,"anchorPoint":{"pointX":0.5,"pointY":0.5}},"texture":"D6FDA76377A4B72BD709A19D5AB53409"}]},{"animations":[],"layers":[],"texturedRectangle":{"singleTextureOpacity":1,"textXHeight":0.45504,"textBaseline":0.74864257812500001,"isBackgroundTexture":false,"isVerticalText":false,"textColor":[0.83576232194900513,0.83576232194900513,0.83576232194900513,1],"textureType":6},"initialState":{"affineTransform":[1,0,0,1,0,0],"masksToBounds":false,"rotation":0,"scale":1,"position":{"pointX":336,"pointY":460},"width":648,"sublayerTransform":[1,0,0,0,0,1,0,0,0,0,1,0,0,0,0,1],"contentsRect":{"y":0,"x":0,"width":1,"height":1},"opacity":1,"edgeAntialiasingMask":0,"height":50,"hidden":true,"anchorPoint":{"pointX":0.5,"pointY":0.5}},"texture":"0418E1174A020D26EEBE5FA4772E2C44"}]},"effects":[],"duration":0.001,"type":"buildIn","attributes":{"direction":0},"name":"apple:bc-appear","objectID":"F3110F88-620E-4F0C-9883-9801311D1424"}],"automaticPlay":false,"hyperlinks":[],"accessibility":[{"text":"JoyFUL LOcal dev","targetRectangle":{"y":54,"x":64,"width":330.98554730415344,"height":42}},{"text":"Introduction","targetRectangle":{"y":308,"x":113.99999809265137,"width":270.096,"height":105}},{"text":"“Joyful Local Dev” ???","targetRectangle":{"y":413,"x":113.99999809265137,"width":479.03999999999996,"height":105}},{"text":"Tools & Techniques","targetRectangle":{"y":518,"x":113.99999809265137,"width":422.06400000000008,"height":105}},{"text":"Agenda","targetRectangle":{"y":174,"x":64,"width":178.21427999999997,"height":71.558220367431659}}],"baseLayer":{"animations":[],"initialState":{"affineTransform":[1,0,0,1,0,0],"masksToBounds":false,"rotation":0,"scale":1,"position":{"pointX":960,"pointY":540},"width":1920,"sublayerTransform":[1,0,0,0,0,1,0,0,0,0,1,0,0,0,0,1],"contentsRect":{"y":0,"x":0,"width":1,"height":1},"opacity":1,"edgeAntialiasingMask":251658240,"height":1080,"hidden":false,"anchorPoint":{"pointX":0.5,"pointY":0.5}},"layers":[{"animations":[],"initialState":{"affineTransform":[1,0,0,1,0,0],"masksToBounds":false,"rotation":0,"scale":1,"position":{"pointX":960,"pointY":540},"width":1920,"sublayerTransform":[1,0,0,0,0,1,0,0,0,0,1,0,0,0,0,1],"contentsRect":{"y":0,"x":0,"width":1,"height":1},"opacity":1,"edgeAntialiasingMask":251658240,"height":1080,"hidden":false,"anchorPoint":{"pointX":0.5,"pointY":0.5}},"layers":[{"animations":[],"initialState":{"affineTransform":[1,0,0,1,0,0],"masksToBounds":false,"rotation":0,"scale":1,"position":{"pointX":960,"pointY":540},"width":1920,"sublayerTransform":[1,0,0,0,0,1,0,0,0,0,1,0,0,0,0,1],"contentsRect":{"y":0,"x":0,"width":1,"height":1},"opacity":1,"edgeAntialiasingMask":251658240,"height":1080,"hidden":false,"anchorPoint":{"pointX":0.5,"pointY":0.5}},"layers":[{"animations":[],"layers":[],"texturedRectangle":{"isBackgroundTexture":true,"singleTextureOpacity":1,"textureType":1,"textBaseline":0,"textXHeight":0,"isVerticalText":false},"initialState":{"affineTransform":[1,0,0,1,0,0],"masksToBounds":false,"rotation":0,"scale":1,"position":{"pointX":960,"pointY":540},"width":1920,"sublayerTransform":[1,0,0,0,0,1,0,0,0,0,1,0,0,0,0,1],"contentsRect":{"y":0,"x":0,"width":1,"height":1},"opacity":1,"edgeAntialiasingMask":0,"height":1080,"hidden":false,"anchorPoint":{"pointX":0.5,"pointY":0.5}},"texture":"F060ECB2D3B13BDD8C493DD73E965B5C"}]}]},{"animations":[],"initialState":{"affineTransform":[1,0,0,1,0,0],"masksToBounds":false,"rotation":0,"scale":1,"position":{"pointX":960,"pointY":540},"width":1920,"sublayerTransform":[1,0,0,0,0,1,0,0,0,0,1,0,0,0,0,1],"contentsRect":{"y":0,"x":0,"width":1,"height":1},"opacity":1,"edgeAntialiasingMask":251658240,"height":1080,"hidden":false,"anchorPoint":{"pointX":0.5,"pointY":0.5}},"layers":[{"animations":[],"initialState":{"affineTransform":[1,0,0,1,0,0],"masksToBounds":false,"rotation":0,"scale":1,"position":{"pointX":961.49998389670304,"pointY":111.97106933606716},"width":1803,"sublayerTransform":[1,0,0,0,0,1,0,0,0,0,1,0,0,0,0,1],"contentsRect":{"y":0,"x":0,"width":1,"height":1},"opacity":1,"edgeAntialiasingMask":251658240,"height":6,"hidden":false,"anchorPoint":{"pointX":0.5,"pointY":0.5}},"layers":[{"animations":[],"layers":[],"texturedRectangle":{"singleTextureOpacity":1,"textXHeight":0,"shapePath":{"lineWidth":1,"flatness":0.59999999999999998,"lineCapStyle":0,"elements":[{"type":"MoveToPoint","points":[[2,3.000055268406868]]},{"type":"AddLine","points":[[1801.9998779296875,2.9710693359375]]}],"windingRule":0,"lineJoinStyle":0,"miterLimit":10},"isBackgroundTexture":true,"textBaseline":0,"isVerticalText":false,"textureType":5},"initialState":{"affineTransform":[1,0,0,1,0,0],"masksToBounds":false,"rotation":0,"scale":1,"position":{"pointX":899.50001610329696,"pointY":1.0289306639328402},"width":1803,"sublayerTransform":[1,0,0,0,0,1,0,0,0,0,1,0,0,0,0,1],"contentsRect":{"y":0,"x":0,"width":1,"height":1},"opacity":1,"edgeAntialiasingMask":0,"height":6,"hidden":false,"anchorPoint":{"pointX":0.5,"pointY":0.5}},"texture":"CC1D75045AACEAD3DAAE3D3B7654F275"}]}]},{"animations":[],"initialState":{"affineTransform":[1,0,0,1,0,0],"masksToBounds":false,"rotation":0,"scale":1,"position":{"pointX":960,"pointY":540},"width":1920,"sublayerTransform":[1,0,0,0,0,1,0,0,0,0,1,0,0,0,0,1],"contentsRect":{"y":0,"x":0,"width":1,"height":1},"opacity":1,"edgeAntialiasingMask":251658240,"height":1080,"hidden":false,"anchorPoint":{"pointX":0.5,"pointY":0.5}},"layers":[{"animations":[],"initialState":{"affineTransform":[1,0,0,1,0,0],"masksToBounds":false,"rotation":0,"scale":1,"position":{"pointX":226,"pointY":64.5},"width":332,"sublayerTransform":[1,0,0,0,0,1,0,0,0,0,1,0,0,0,0,1],"contentsRect":{"y":0,"x":0,"width":1,"height":1},"opacity":1,"edgeAntialiasingMask":251658240,"height":29,"hidden":false,"anchorPoint":{"pointX":0.5,"pointY":0.5}},"layers":[{"animations":[],"layers":[],"texturedRectangle":{"singleTextureOpacity":1,"textXHeight":0.89102909482758619,"textBaseline":0.92625269396551724,"isBackgroundTexture":true,"isVerticalText":false,"textColor":[0.83529406785964966,0.83529418706893921,0.83959966897964478,1],"textureType":6},"initialState":{"affineTransform":[1,0,0,1,0,0],"masksToBounds":false,"rotation":0,"scale":1,"position":{"pointX":169,"pointY":25.5},"width":332,"sublayerTransform":[1,0,0,0,0,1,0,0,0,0,1,0,0,0,0,1],"contentsRect":{"y":0,"x":0,"width":1,"height":1},"opacity":1,"edgeAntialiasingMask":0,"height":29,"hidden":false,"anchorPoint":{"pointX":0.5,"pointY":0.5}},"texture":"EFF14D30B06EA00E9E52AFFF50E90B03"}]}]},{"animations":[],"initialState":{"affineTransform":[1,0,0,1,0,0],"masksToBounds":false,"rotation":0,"scale":1,"position":{"pointX":960,"pointY":540},"width":1920,"sublayerTransform":[1,0,0,0,0,1,0,0,0,0,1,0,0,0,0,1],"contentsRect":{"y":0,"x":0,"width":1,"height":1},"opacity":1,"edgeAntialiasingMask":251658240,"height":1080,"hidden":false,"anchorPoint":{"pointX":0.5,"pointY":0.5}},"layers":[{"animations":[],"initialState":{"affineTransform":[1,0,0,1,0,0],"masksToBounds":false,"rotation":0,"scale":1,"position":{"pointX":150.5,"pointY":198},"width":181,"sublayerTransform":[1,0,0,0,0,1,0,0,0,0,1,0,0,0,0,1],"contentsRect":{"y":0,"x":0,"width":1,"height":1},"opacity":1,"edgeAntialiasingMask":251658240,"height":56,"hidden":false,"anchorPoint":{"pointX":0.5,"pointY":0.5}},"layers":[{"animations":[],"layers":[],"texturedRectangle":{"singleTextureOpacity":1,"textXHeight":0.65375839285714288,"textBaseline":0.96003831863403322,"isBackgroundTexture":true,"isVerticalText":false,"textColor":[0.2039216160774231,0.64705884456634521,0.85490202903747559,1],"textureType":6},"initialState":{"affineTransform":[1,0,0,1,0,0],"masksToBounds":false,"rotation":0,"scale":1,"position":{"pointX":93.5,"pointY":29},"width":181,"sublayerTransform":[1,0,0,0,0,1,0,0,0,0,1,0,0,0,0,1],"contentsRect":{"y":0,"x":0,"width":1,"height":1},"opacity":1,"edgeAntialiasingMask":0,"height":56,"hidden":false,"anchorPoint":{"pointX":0.5,"pointY":0.5}},"texture":"EA314A6407CB6C945B4C0DB198AACAF2"}]}]},{"animations":[],"initialState":{"affineTransform":[1,0,0,1,0,0],"masksToBounds":false,"rotation":0,"scale":1,"position":{"pointX":960,"pointY":540},"width":1920,"sublayerTransform":[1,0,0,0,0,1,0,0,0,0,1,0,0,0,0,1],"contentsRect":{"y":0,"x":0,"width":1,"height":1},"opacity":1,"edgeAntialiasingMask":251658240,"height":1080,"hidden":false,"anchorPoint":{"pointX":0.5,"pointY":0.5}},"layers":[{"animations":[],"initialState":{"affineTransform":[1,0,0,1,0,0],"masksToBounds":false,"rotation":0,"scale":1,"position":{"pointX":384,"pointY":539},"width":648,"sublayerTransform":[1,0,0,0,0,1,0,0,0,0,1,0,0,0,0,1],"contentsRect":{"y":0,"x":0,"width":1,"height":1},"opacity":1,"edgeAntialiasingMask":251658240,"height":470,"hidden":false,"anchorPoint":{"pointX":0.5,"pointY":0.5}},"objectID":"F3110F88-620E-4F0C-9883-9801311D1424","layers":[{"animations":[],"layers":[],"texturedRectangle":{"singleTextureOpacity":1,"textXHeight":0.55492682926829262,"textBaseline":0.9129787538109756,"isBackgroundTexture":false,"isVerticalText":false,"textColor":[0.83576232194900513,0.83576232194900513,0.83576232194900513,1],"textureType":6},"initialState":{"affineTransform":[1,0,0,1,0,0],"masksToBounds":false,"rotation":0,"scale":1,"position":{"pointX":167,"pointY":35.5},"width":310,"sublayerTransform":[1,0,0,0,0,1,0,0,0,0,1,0,0,0,0,1],"contentsRect":{"y":0,"x":0,"width":1,"height":1},"opacity":1,"edgeAntialiasingMask":0,"height":41,"hidden":false,"anchorPoint":{"pointX":0.5,"pointY":0.5}},"texture":"338FB3DAC9706D521D9A50392316EF03"},{"animations":[],"layers":[],"texturedRectangle":{"singleTextureOpacity":1,"textXHeight":0.44611764705882351,"textBaseline":0.75357115502450978,"isBackgroundTexture":false,"isVerticalText":false,"textColor":[0.83576232194900513,0.83576232194900513,0.83576232194900513,1],"textureType":6},"initialState":{"affineTransform":[1,0,0,1,0,0],"masksToBounds":false,"rotation":0,"scale":1,"position":{"pointX":272.5,"pointY":144.5},"width":521,"sublayerTransform":[1,0,0,0,0,1,0,0,0,0,1,0,0,0,0,1],"contentsRect":{"y":0,"x":0,"width":1,"height":1},"opacity":1,"edgeAntialiasingMask":0,"height":51,"hidden":false,"anchorPoint":{"pointX":0.5,"pointY":0.5}},"texture":"B91F7CE3C9C210F11E0B0C8265F67F38"},{"animations":[],"layers":[],"texturedRectangle":{"singleTextureOpacity":1,"textXHeight":0.45504,"textBaseline":0.74864257812500001,"isBackgroundTexture":false,"isVerticalText":false,"textColor":[0.83576232194900513,0.83576232194900513,0.83576232194900513,1],"textureType":6},"initialState":{"affineTransform":[1,0,0,1,0,0],"masksToBounds":false,"rotation":0,"scale":1,"position":{"pointX":244,"pointY":250},"width":464,"sublayerTransform":[1,0,0,0,0,1,0,0,0,0,1,0,0,0,0,1],"contentsRect":{"y":0,"x":0,"width":1,"height":1},"opacity":1,"edgeAntialiasingMask":0,"height":50,"hidden":false,"anchorPoint":{"pointX":0.5,"pointY":0.5}},"texture":"764AC2DAD017313B8416EA5D04A04BF8"},{"animations":[],"layers":[],"texturedRectangle":{"singleTextureOpacity":1,"textXHeight":0.58338461538461539,"textBaseline":0.90851612580128205,"isBackgroundTexture":false,"isVerticalText":false,"textColor":[0.83576232194900513,0.83576232194900513,0.83576232194900513,1],"textureType":6},"initialState":{"affineTransform":[1,0,0,1,0,0],"masksToBounds":false,"rotation":0,"scale":1,"position":{"pointX":100.5,"pointY":351.5},"width":177,"sublayerTransform":[1,0,0,0,0,1,0,0,0,0,1,0,0,0,0,1],"contentsRect":{"y":0,"x":0,"width":1,"height":1},"opacity":1,"edgeAntialiasingMask":0,"height":39,"hidden":true,"anchorPoint":{"pointX":0.5,"pointY":0.5}},"texture":"D6FDA76377A4B72BD709A19D5AB53409"},{"animations":[],"layers":[],"texturedRectangle":{"singleTextureOpacity":1,"textXHeight":0.45504,"textBaseline":0.74864257812500001,"isBackgroundTexture":false,"isVerticalText":false,"textColor":[0.83576232194900513,0.83576232194900513,0.83576232194900513,1],"textureType":6},"initialState":{"affineTransform":[1,0,0,1,0,0],"masksToBounds":false,"rotation":0,"scale":1,"position":{"pointX":336,"pointY":460},"width":648,"sublayerTransform":[1,0,0,0,0,1,0,0,0,0,1,0,0,0,0,1],"contentsRect":{"y":0,"x":0,"width":1,"height":1},"opacity":1,"edgeAntialiasingMask":0,"height":50,"hidden":true,"anchorPoint":{"pointX":0.5,"pointY":0.5}},"texture":"0418E1174A020D26EEBE5FA4772E2C44"}]}]}]}},{"effects":[{"beginTime":0,"baseLayer":{"animations":[],"initialState":{"affineTransform":[1,0,0,1,0,0],"masksToBounds":false,"rotation":0,"scale":1,"position":{"pointX":384,"pointY":539},"width":648,"sublayerTransform":[1,0,0,0,0,1,0,0,0,0,1,0,0,0,0,1],"contentsRect":{"y":0,"x":0,"width":1,"height":1},"opacity":1,"edgeAntialiasingMask":251658240,"height":470,"hidden":false,"anchorPoint":{"pointX":0.5,"pointY":0.5}},"objectID":"F3110F88-620E-4F0C-9883-9801311D1424","layers":[{"animations":[],"layers":[],"texturedRectangle":{"singleTextureOpacity":1,"textXHeight":0.55492682926829262,"textBaseline":0.9129787538109756,"isBackgroundTexture":false,"isVerticalText":false,"textColor":[0.83576232194900513,0.83576232194900513,0.83576232194900513,1],"textureType":6},"initialState":{"affineTransform":[1,0,0,1,0,0],"masksToBounds":false,"rotation":0,"scale":1,"position":{"pointX":167,"pointY":35.5},"width":310,"sublayerTransform":[1,0,0,0,0,1,0,0,0,0,1,0,0,0,0,1],"contentsRect":{"y":0,"x":0,"width":1,"height":1},"opacity":1,"edgeAntialiasingMask":0,"height":41,"hidden":false,"anchorPoint":{"pointX":0.5,"pointY":0.5}},"texture":"338FB3DAC9706D521D9A50392316EF03"},{"animations":[],"layers":[],"texturedRectangle":{"singleTextureOpacity":1,"textXHeight":0.44611764705882351,"textBaseline":0.75357115502450978,"isBackgroundTexture":false,"isVerticalText":false,"textColor":[0.83576232194900513,0.83576232194900513,0.83576232194900513,1],"textureType":6},"initialState":{"affineTransform":[1,0,0,1,0,0],"masksToBounds":false,"rotation":0,"scale":1,"position":{"pointX":272.5,"pointY":144.5},"width":521,"sublayerTransform":[1,0,0,0,0,1,0,0,0,0,1,0,0,0,0,1],"contentsRect":{"y":0,"x":0,"width":1,"height":1},"opacity":1,"edgeAntialiasingMask":0,"height":51,"hidden":false,"anchorPoint":{"pointX":0.5,"pointY":0.5}},"texture":"B91F7CE3C9C210F11E0B0C8265F67F38"},{"animations":[],"layers":[],"texturedRectangle":{"singleTextureOpacity":1,"textXHeight":0.45504,"textBaseline":0.74864257812500001,"isBackgroundTexture":false,"isVerticalText":false,"textColor":[0.83576232194900513,0.83576232194900513,0.83576232194900513,1],"textureType":6},"initialState":{"affineTransform":[1,0,0,1,0,0],"masksToBounds":false,"rotation":0,"scale":1,"position":{"pointX":244,"pointY":250},"width":464,"sublayerTransform":[1,0,0,0,0,1,0,0,0,0,1,0,0,0,0,1],"contentsRect":{"y":0,"x":0,"width":1,"height":1},"opacity":1,"edgeAntialiasingMask":0,"height":50,"hidden":false,"anchorPoint":{"pointX":0.5,"pointY":0.5}},"texture":"764AC2DAD017313B8416EA5D04A04BF8"},{"animations":[],"layers":[],"texturedRectangle":{"singleTextureOpacity":1,"textXHeight":0.58338461538461539,"textBaseline":0.90851612580128205,"isBackgroundTexture":false,"isVerticalText":false,"textColor":[0.83576232194900513,0.83576232194900513,0.83576232194900513,1],"textureType":6},"initialState":{"affineTransform":[1,0,0,1,0,0],"masksToBounds":false,"rotation":0,"scale":1,"position":{"pointX":100.5,"pointY":351.5},"width":177,"sublayerTransform":[1,0,0,0,0,1,0,0,0,0,1,0,0,0,0,1],"contentsRect":{"y":0,"x":0,"width":1,"height":1},"opacity":1,"edgeAntialiasingMask":0,"height":39,"hidden":false,"anchorPoint":{"pointX":0.5,"pointY":0.5}},"texture":"D6FDA76377A4B72BD709A19D5AB53409"},{"animations":[],"initialState":{"affineTransform":[1,0,0,1,0,0],"masksToBounds":false,"rotation":0,"scale":1,"position":{"pointX":900,"pointY":236},"width":648,"sublayerTransform":[1,0,0,0,0,1,0,0,0,0,1,-0.00035007912466775983,0,0,0,1],"contentsRect":{"y":0,"x":0,"width":1,"height":1},"opacity":1,"edgeAntialiasingMask":251658240,"height":470,"hidden":false,"anchorPoint":{"pointX":1.3888888888888888,"pointY":0.50212765957446803}},"layers":[{"animations":[{"additive":false,"timeOffset":0,"beginTime":1e-100,"repeatCount":0,"fillMode":"both","duration":0.001,"autoreverses":false,"animations":[{"additive":false,"timeOffset":0,"beginTime":0,"from":{"scalar":true},"repeatCount":0,"fillMode":"both","duration":0.0001,"autoreverses":false,"property":"hidden","to":{"scalar":false},"removedOnCompletion":true},{"additive":false,"timeOffset":0,"beginTime":0.0001,"from":{"scalar":false},"repeatCount":0,"fillMode":"forwards","duration":0.00089999999999999998,"autoreverses":false,"property":"hidden","to":{"scalar":false},"removedOnCompletion":true}],"removedOnCompletion":false}],"layers":[],"texturedRectangle":{"singleTextureOpacity":1,"textXHeight":0.45504,"textBaseline":0.74864257812500001,"isBackgroundTexture":false,"isVerticalText":false,"textColor":[0.83576232194900513,0.83576232194900513,0.83576232194900513,1],"textureType":6},"initialState":{"affineTransform":[1,0,0,1,0,0],"masksToBounds":false,"rotation":0,"scale":1,"position":{"pointX":336,"pointY":460},"width":648,"sublayerTransform":[1,0,0,0,0,1,0,0,0,0,1,0,0,0,0,1],"contentsRect":{"y":0,"x":0,"width":1,"height":1},"opacity":1,"edgeAntialiasingMask":0,"height":50,"hidden":true,"anchorPoint":{"pointX":0.5,"pointY":0.5}},"texture":"0418E1174A020D26EEBE5FA4772E2C44"}]}]},"effects":[],"duration":0.001,"type":"buildIn","attributes":{"direction":0},"name":"apple:bc-appear","objectID":"F3110F88-620E-4F0C-9883-9801311D1424"}],"automaticPlay":false,"hyperlinks":[],"accessibility":[{"text":"JoyFUL LOcal dev","targetRectangle":{"y":54,"x":64,"width":330.98554730415344,"height":42}},{"text":"Agenda","targetRectangle":{"y":174,"x":64,"width":178.21427999999997,"height":71.558220367431659}}],"baseLayer":{"animations":[],"initialState":{"affineTransform":[1,0,0,1,0,0],"masksToBounds":false,"rotation":0,"scale":1,"position":{"pointX":960,"pointY":540},"width":1920,"sublayerTransform":[1,0,0,0,0,1,0,0,0,0,1,0,0,0,0,1],"contentsRect":{"y":0,"x":0,"width":1,"height":1},"opacity":1,"edgeAntialiasingMask":251658240,"height":1080,"hidden":false,"anchorPoint":{"pointX":0.5,"pointY":0.5}},"layers":[{"animations":[],"initialState":{"affineTransform":[1,0,0,1,0,0],"masksToBounds":false,"rotation":0,"scale":1,"position":{"pointX":960,"pointY":540},"width":1920,"sublayerTransform":[1,0,0,0,0,1,0,0,0,0,1,0,0,0,0,1],"contentsRect":{"y":0,"x":0,"width":1,"height":1},"opacity":1,"edgeAntialiasingMask":251658240,"height":1080,"hidden":false,"anchorPoint":{"pointX":0.5,"pointY":0.5}},"layers":[{"animations":[],"initialState":{"affineTransform":[1,0,0,1,0,0],"masksToBounds":false,"rotation":0,"scale":1,"position":{"pointX":960,"pointY":540},"width":1920,"sublayerTransform":[1,0,0,0,0,1,0,0,0,0,1,0,0,0,0,1],"contentsRect":{"y":0,"x":0,"width":1,"height":1},"opacity":1,"edgeAntialiasingMask":251658240,"height":1080,"hidden":false,"anchorPoint":{"pointX":0.5,"pointY":0.5}},"layers":[{"animations":[],"layers":[],"texturedRectangle":{"isBackgroundTexture":true,"singleTextureOpacity":1,"textureType":1,"textBaseline":0,"textXHeight":0,"isVerticalText":false},"initialState":{"affineTransform":[1,0,0,1,0,0],"masksToBounds":false,"rotation":0,"scale":1,"position":{"pointX":960,"pointY":540},"width":1920,"sublayerTransform":[1,0,0,0,0,1,0,0,0,0,1,0,0,0,0,1],"contentsRect":{"y":0,"x":0,"width":1,"height":1},"opacity":1,"edgeAntialiasingMask":0,"height":1080,"hidden":false,"anchorPoint":{"pointX":0.5,"pointY":0.5}},"texture":"F060ECB2D3B13BDD8C493DD73E965B5C"}]}]},{"animations":[],"initialState":{"affineTransform":[1,0,0,1,0,0],"masksToBounds":false,"rotation":0,"scale":1,"position":{"pointX":960,"pointY":540},"width":1920,"sublayerTransform":[1,0,0,0,0,1,0,0,0,0,1,0,0,0,0,1],"contentsRect":{"y":0,"x":0,"width":1,"height":1},"opacity":1,"edgeAntialiasingMask":251658240,"height":1080,"hidden":false,"anchorPoint":{"pointX":0.5,"pointY":0.5}},"layers":[{"animations":[],"initialState":{"affineTransform":[1,0,0,1,0,0],"masksToBounds":false,"rotation":0,"scale":1,"position":{"pointX":961.49998389670304,"pointY":111.97106933606716},"width":1803,"sublayerTransform":[1,0,0,0,0,1,0,0,0,0,1,0,0,0,0,1],"contentsRect":{"y":0,"x":0,"width":1,"height":1},"opacity":1,"edgeAntialiasingMask":251658240,"height":6,"hidden":false,"anchorPoint":{"pointX":0.5,"pointY":0.5}},"layers":[{"animations":[],"layers":[],"texturedRectangle":{"singleTextureOpacity":1,"textXHeight":0,"shapePath":{"lineWidth":1,"flatness":0.59999999999999998,"lineCapStyle":0,"elements":[{"type":"MoveToPoint","points":[[2,3.000055268406868]]},{"type":"AddLine","points":[[1801.9998779296875,2.9710693359375]]}],"windingRule":0,"lineJoinStyle":0,"miterLimit":10},"isBackgroundTexture":true,"textBaseline":0,"isVerticalText":false,"textureType":5},"initialState":{"affineTransform":[1,0,0,1,0,0],"masksToBounds":false,"rotation":0,"scale":1,"position":{"pointX":899.50001610329696,"pointY":1.0289306639328402},"width":1803,"sublayerTransform":[1,0,0,0,0,1,0,0,0,0,1,0,0,0,0,1],"contentsRect":{"y":0,"x":0,"width":1,"height":1},"opacity":1,"edgeAntialiasingMask":0,"height":6,"hidden":false,"anchorPoint":{"pointX":0.5,"pointY":0.5}},"texture":"CC1D75045AACEAD3DAAE3D3B7654F275"}]}]},{"animations":[],"initialState":{"affineTransform":[1,0,0,1,0,0],"masksToBounds":false,"rotation":0,"scale":1,"position":{"pointX":960,"pointY":540},"width":1920,"sublayerTransform":[1,0,0,0,0,1,0,0,0,0,1,0,0,0,0,1],"contentsRect":{"y":0,"x":0,"width":1,"height":1},"opacity":1,"edgeAntialiasingMask":251658240,"height":1080,"hidden":false,"anchorPoint":{"pointX":0.5,"pointY":0.5}},"layers":[{"animations":[],"initialState":{"affineTransform":[1,0,0,1,0,0],"masksToBounds":false,"rotation":0,"scale":1,"position":{"pointX":226,"pointY":64.5},"width":332,"sublayerTransform":[1,0,0,0,0,1,0,0,0,0,1,0,0,0,0,1],"contentsRect":{"y":0,"x":0,"width":1,"height":1},"opacity":1,"edgeAntialiasingMask":251658240,"height":29,"hidden":false,"anchorPoint":{"pointX":0.5,"pointY":0.5}},"layers":[{"animations":[],"layers":[],"texturedRectangle":{"singleTextureOpacity":1,"textXHeight":0.89102909482758619,"textBaseline":0.92625269396551724,"isBackgroundTexture":true,"isVerticalText":false,"textColor":[0.83529406785964966,0.83529418706893921,0.83959966897964478,1],"textureType":6},"initialState":{"affineTransform":[1,0,0,1,0,0],"masksToBounds":false,"rotation":0,"scale":1,"position":{"pointX":169,"pointY":25.5},"width":332,"sublayerTransform":[1,0,0,0,0,1,0,0,0,0,1,0,0,0,0,1],"contentsRect":{"y":0,"x":0,"width":1,"height":1},"opacity":1,"edgeAntialiasingMask":0,"height":29,"hidden":false,"anchorPoint":{"pointX":0.5,"pointY":0.5}},"texture":"EFF14D30B06EA00E9E52AFFF50E90B03"}]}]},{"animations":[],"initialState":{"affineTransform":[1,0,0,1,0,0],"masksToBounds":false,"rotation":0,"scale":1,"position":{"pointX":960,"pointY":540},"width":1920,"sublayerTransform":[1,0,0,0,0,1,0,0,0,0,1,0,0,0,0,1],"contentsRect":{"y":0,"x":0,"width":1,"height":1},"opacity":1,"edgeAntialiasingMask":251658240,"height":1080,"hidden":false,"anchorPoint":{"pointX":0.5,"pointY":0.5}},"layers":[{"animations":[],"initialState":{"affineTransform":[1,0,0,1,0,0],"masksToBounds":false,"rotation":0,"scale":1,"position":{"pointX":150.5,"pointY":198},"width":181,"sublayerTransform":[1,0,0,0,0,1,0,0,0,0,1,0,0,0,0,1],"contentsRect":{"y":0,"x":0,"width":1,"height":1},"opacity":1,"edgeAntialiasingMask":251658240,"height":56,"hidden":false,"anchorPoint":{"pointX":0.5,"pointY":0.5}},"layers":[{"animations":[],"layers":[],"texturedRectangle":{"singleTextureOpacity":1,"textXHeight":0.65375839285714288,"textBaseline":0.96003831863403322,"isBackgroundTexture":true,"isVerticalText":false,"textColor":[0.2039216160774231,0.64705884456634521,0.85490202903747559,1],"textureType":6},"initialState":{"affineTransform":[1,0,0,1,0,0],"masksToBounds":false,"rotation":0,"scale":1,"position":{"pointX":93.5,"pointY":29},"width":181,"sublayerTransform":[1,0,0,0,0,1,0,0,0,0,1,0,0,0,0,1],"contentsRect":{"y":0,"x":0,"width":1,"height":1},"opacity":1,"edgeAntialiasingMask":0,"height":56,"hidden":false,"anchorPoint":{"pointX":0.5,"pointY":0.5}},"texture":"EA314A6407CB6C945B4C0DB198AACAF2"}]}]},{"animations":[],"initialState":{"affineTransform":[1,0,0,1,0,0],"masksToBounds":false,"rotation":0,"scale":1,"position":{"pointX":960,"pointY":540},"width":1920,"sublayerTransform":[1,0,0,0,0,1,0,0,0,0,1,0,0,0,0,1],"contentsRect":{"y":0,"x":0,"width":1,"height":1},"opacity":1,"edgeAntialiasingMask":251658240,"height":1080,"hidden":false,"anchorPoint":{"pointX":0.5,"pointY":0.5}},"layers":[{"animations":[],"initialState":{"affineTransform":[1,0,0,1,0,0],"masksToBounds":false,"rotation":0,"scale":1,"position":{"pointX":384,"pointY":539},"width":648,"sublayerTransform":[1,0,0,0,0,1,0,0,0,0,1,0,0,0,0,1],"contentsRect":{"y":0,"x":0,"width":1,"height":1},"opacity":1,"edgeAntialiasingMask":251658240,"height":470,"hidden":false,"anchorPoint":{"pointX":0.5,"pointY":0.5}},"objectID":"F3110F88-620E-4F0C-9883-9801311D1424","layers":[{"animations":[],"layers":[],"texturedRectangle":{"singleTextureOpacity":1,"textXHeight":0.55492682926829262,"textBaseline":0.9129787538109756,"isBackgroundTexture":false,"isVerticalText":false,"textColor":[0.83576232194900513,0.83576232194900513,0.83576232194900513,1],"textureType":6},"initialState":{"affineTransform":[1,0,0,1,0,0],"masksToBounds":false,"rotation":0,"scale":1,"position":{"pointX":167,"pointY":35.5},"width":310,"sublayerTransform":[1,0,0,0,0,1,0,0,0,0,1,0,0,0,0,1],"contentsRect":{"y":0,"x":0,"width":1,"height":1},"opacity":1,"edgeAntialiasingMask":0,"height":41,"hidden":false,"anchorPoint":{"pointX":0.5,"pointY":0.5}},"texture":"338FB3DAC9706D521D9A50392316EF03"},{"animations":[],"layers":[],"texturedRectangle":{"singleTextureOpacity":1,"textXHeight":0.44611764705882351,"textBaseline":0.75357115502450978,"isBackgroundTexture":false,"isVerticalText":false,"textColor":[0.83576232194900513,0.83576232194900513,0.83576232194900513,1],"textureType":6},"initialState":{"affineTransform":[1,0,0,1,0,0],"masksToBounds":false,"rotation":0,"scale":1,"position":{"pointX":272.5,"pointY":144.5},"width":521,"sublayerTransform":[1,0,0,0,0,1,0,0,0,0,1,0,0,0,0,1],"contentsRect":{"y":0,"x":0,"width":1,"height":1},"opacity":1,"edgeAntialiasingMask":0,"height":51,"hidden":false,"anchorPoint":{"pointX":0.5,"pointY":0.5}},"texture":"B91F7CE3C9C210F11E0B0C8265F67F38"},{"animations":[],"layers":[],"texturedRectangle":{"singleTextureOpacity":1,"textXHeight":0.45504,"textBaseline":0.74864257812500001,"isBackgroundTexture":false,"isVerticalText":false,"textColor":[0.83576232194900513,0.83576232194900513,0.83576232194900513,1],"textureType":6},"initialState":{"affineTransform":[1,0,0,1,0,0],"masksToBounds":false,"rotation":0,"scale":1,"position":{"pointX":244,"pointY":250},"width":464,"sublayerTransform":[1,0,0,0,0,1,0,0,0,0,1,0,0,0,0,1],"contentsRect":{"y":0,"x":0,"width":1,"height":1},"opacity":1,"edgeAntialiasingMask":0,"height":50,"hidden":false,"anchorPoint":{"pointX":0.5,"pointY":0.5}},"texture":"764AC2DAD017313B8416EA5D04A04BF8"},{"animations":[],"layers":[],"texturedRectangle":{"singleTextureOpacity":1,"textXHeight":0.58338461538461539,"textBaseline":0.90851612580128205,"isBackgroundTexture":false,"isVerticalText":false,"textColor":[0.83576232194900513,0.83576232194900513,0.83576232194900513,1],"textureType":6},"initialState":{"affineTransform":[1,0,0,1,0,0],"masksToBounds":false,"rotation":0,"scale":1,"position":{"pointX":100.5,"pointY":351.5},"width":177,"sublayerTransform":[1,0,0,0,0,1,0,0,0,0,1,0,0,0,0,1],"contentsRect":{"y":0,"x":0,"width":1,"height":1},"opacity":1,"edgeAntialiasingMask":0,"height":39,"hidden":false,"anchorPoint":{"pointX":0.5,"pointY":0.5}},"texture":"D6FDA76377A4B72BD709A19D5AB53409"},{"animations":[],"layers":[],"texturedRectangle":{"singleTextureOpacity":1,"textXHeight":0.45504,"textBaseline":0.74864257812500001,"isBackgroundTexture":false,"isVerticalText":false,"textColor":[0.83576232194900513,0.83576232194900513,0.83576232194900513,1],"textureType":6},"initialState":{"affineTransform":[1,0,0,1,0,0],"masksToBounds":false,"rotation":0,"scale":1,"position":{"pointX":336,"pointY":460},"width":648,"sublayerTransform":[1,0,0,0,0,1,0,0,0,0,1,0,0,0,0,1],"contentsRect":{"y":0,"x":0,"width":1,"height":1},"opacity":1,"edgeAntialiasingMask":0,"height":50,"hidden":true,"anchorPoint":{"pointX":0.5,"pointY":0.5}},"texture":"0418E1174A020D26EEBE5FA4772E2C44"}]}]}]}},{"effects":[{"beginTime":0,"baseLayer":{"animations":[],"initialState":{"affineTransform":[1,0,0,1,0,0],"masksToBounds":false,"rotation":0,"scale":1,"position":{"pointX":960,"pointY":540},"width":1920,"sublayerTransform":[1,0,0,0,0,1,0,0,0,0,1,0,0,0,0,1],"contentsRect":{"y":0,"x":0,"width":1,"height":1},"opacity":1,"edgeAntialiasingMask":251658240,"height":1080,"hidden":false,"anchorPoint":{"pointX":0.5,"pointY":0.5}},"objectID":"0","layers":[{"animations":[],"initialState":{"affineTransform":[1,0,0,1,0,0],"masksToBounds":false,"rotation":0,"scale":1,"position":{"pointX":960,"pointY":540},"width":1920,"sublayerTransform":[1,0,0,0,0,1,0,0,0,0,1,-0.00035007912466775983,0,0,0,1],"contentsRect":{"y":0,"x":0,"width":1,"height":1},"opacity":1,"edgeAntialiasingMask":251658240,"height":1080,"hidden":false,"anchorPoint":{"pointX":0.5,"pointY":0.5}},"layers":[{"animations":[],"layers":[],"texturedRectangle":{"isBackgroundTexture":false,"singleTextureOpacity":1,"textureType":0,"textBaseline":0,"textXHeight":0,"isVerticalText":false},"initialState":{"affineTransform":[1,0,0,1,0,0],"masksToBounds":false,"rotation":0,"scale":1,"position":{"pointX":960,"pointY":540},"width":1920,"sublayerTransform":[1,0,0,0,0,1,0,0,0,0,1,0,0,0,0,1],"contentsRect":{"y":0,"x":0,"width":1,"height":1},"opacity":1,"edgeAntialiasingMask":0,"height":1080,"hidden":false,"anchorPoint":{"pointX":0.5,"pointY":0.5}},"texture":"6DA4FD3155B1C94EE0AADF8C1DE99484"},{"animations":[{"additive":false,"timeOffset":0,"beginTime":0,"from":{"scalar":false},"repeatCount":0,"fillMode":"both","duration":0.001,"autoreverses":false,"property":"hidden","to":{"scalar":true},"removedOnCompletion":false}],"layers":[],"texturedRectangle":{"isBackgroundTexture":false,"singleTextureOpacity":1,"textureType":0,"textBaseline":0,"textXHeight":0,"isVerticalText":false},"initialState":{"affineTransform":[1,0,0,1,0,0],"masksToBounds":false,"rotation":0,"scale":1,"position":{"pointX":960,"pointY":540},"width":1920,"sublayerTransform":[1,0,0,0,0,1,0,0,0,0,1,0,0,0,0,1],"contentsRect":{"y":0,"x":0,"width":1,"height":1},"opacity":1,"edgeAntialiasingMask":0,"height":1080,"hidden":false,"anchorPoint":{"pointX":0.5,"pointY":0.5}},"texture":"B79D2036AB1E194906B9078B775C0A80"}]}]},"effects":[],"duration":0.001,"type":"transition","attributes":{"direction":0},"name":"none","objectID":"0"}],"automaticPlay":false,"hyperlinks":[],"accessibility":[{"text":"JoyFUL LOcal dev","targetRectangle":{"y":54,"x":64,"width":330.98554730415344,"height":42}},{"text":"Introduction","targetRectangle":{"y":308,"x":113.99999809265137,"width":270.096,"height":105}},{"text":"“Joyful Local Dev” ???","targetRectangle":{"y":413,"x":113.99999809265137,"width":479.03999999999996,"height":105}},{"text":"Tools & Techniques","targetRectangle":{"y":518,"x":113.99999809265137,"width":422.06400000000008,"height":105}},{"text":"Demo","targetRectangle":{"y":623,"x":113.99999809265137,"width":135.88800000000001,"height":105}},{"text":"Final Thoughts & Questions","targetRectangle":{"y":728,"x":113.99999809265137,"width":606.096,"height":66}},{"text":"Agenda","targetRectangle":{"y":174,"x":64,"width":178.21427999999997,"height":71.558220367431659}}],"baseLayer":{"animations":[],"initialState":{"affineTransform":[1,0,0,1,0,0],"masksToBounds":false,"rotation":0,"scale":1,"position":{"pointX":960,"pointY":540},"width":1920,"sublayerTransform":[1,0,0,0,0,1,0,0,0,0,1,0,0,0,0,1],"contentsRect":{"y":0,"x":0,"width":1,"height":1},"opacity":1,"edgeAntialiasingMask":251658240,"height":1080,"hidden":false,"anchorPoint":{"pointX":0.5,"pointY":0.5}},"objectID":"0","layers":[{"animations":[],"initialState":{"affineTransform":[1,0,0,1,0,0],"masksToBounds":false,"rotation":0,"scale":1,"position":{"pointX":960,"pointY":540},"width":1920,"sublayerTransform":[1,0,0,0,0,1,0,0,0,0,1,-0.00035007912466775983,0,0,0,1],"contentsRect":{"y":0,"x":0,"width":1,"height":1},"opacity":1,"edgeAntialiasingMask":251658240,"height":1080,"hidden":false,"anchorPoint":{"pointX":0.5,"pointY":0.5}},"layers":[{"animations":[],"layers":[],"texturedRectangle":{"isBackgroundTexture":false,"singleTextureOpacity":1,"textureType":0,"textBaseline":0,"textXHeight":0,"isVerticalText":false},"initialState":{"affineTransform":[1,0,0,1,0,0],"masksToBounds":false,"rotation":0,"scale":1,"position":{"pointX":960,"pointY":540},"width":1920,"sublayerTransform":[1,0,0,0,0,1,0,0,0,0,1,0,0,0,0,1],"contentsRect":{"y":0,"x":0,"width":1,"height":1},"opacity":1,"edgeAntialiasingMask":0,"height":1080,"hidden":false,"anchorPoint":{"pointX":0.5,"pointY":0.5}},"texture":"B79D2036AB1E194906B9078B775C0A80"}]}]}}]}